[
  {
    "id": 164146661,
    "bedrooms": 3,
    "bathrooms": 1,
    "numberOfImages": 10,
    "numberOfFloorplans": 1,
    "numberOfVirtualTours": 0,
    "summary": "***EAT IN KITCHEN***",
    "displayAddress": "Lenham House, Staple Street, SE1",
    "countryCode": "GB",
    "location": {
      "latitude": 51.4989,
      "longitude": -0.087132
    },
    "images": [
      {
        "srcUrl": "https://media.rightmove.co.uk:443/dir/crop/10:9-16:9/106k/105856/164146661/105856_3429_IMG_00_0000_max_476x317.jpeg",
        "url": "106k/105856/164146661/105856_3429_IMG_00_0000.jpeg",
        "caption": null
      },
      {
        "srcUrl": "https://media.rightmove.co.uk:443/dir/crop/10:9-16:9/106k/105856/164146661/105856_3429_IMG_01_0000_max_476x317.jpeg",
        "url": "106k/105856/164146661/105856_3429_IMG_01_0000.jpeg",
        "caption": null
      },
      {
        "srcUrl": "https://media.rightmove.co.uk:443/dir/crop/10:9-16:9/106k/105856/164146661/105856_3429_IMG_02_0000_max_476x317.jpeg",
        "url": "106k/105856/164146661/105856_3429_IMG_02_0000.jpeg",
        "caption": null
      },
      {
        "srcUrl": "https://media.rightmove.co.uk:443/dir/crop/10:9-16:9/106k/105856/164146661/105856_3429_IMG_03_0000_max_476x317.jpeg",
        "url": "106k/105856/164146661/105856_3429_IMG_03_0000.jpeg",
        "caption": null
      },
      {
        "srcUrl": "https://media.rightmove.co.uk:443/dir/crop/10:9-16:9/106k/105856/164146661/105856_3429_IMG_04_0000_max_476x317.jpeg",
        "url": "106k/105856/164146661/105856_3429_IMG_04_0000.jpeg",
        "caption": null
      },
      {
        "srcUrl": "https://media.rightmove.co.uk:443/dir/crop/10:9-16:9/106k/105856/164146661/105856_3429_IMG_05_0000_max_476x317.jpeg",
        "url": "106k/105856/164146661/105856_3429_IMG_05_0000.jpeg",
        "caption": null
      },
      {
        "srcUrl": "https://media.rightmove.co.uk:443/dir/crop/10:9-16:9/106k/105856/164146661/105856_3429_IMG_06_0000_max_476x317.jpeg",
        "url": "106k/105856/164146661/105856_3429_IMG_06_0000.jpeg",
        "caption": null
      },
      {
        "srcUrl": "https://media.rightmove.co.uk:443/dir/crop/10:9-16:9/106k/105856/164146661/105856_3429_IMG_07_0000_max_476x317.jpeg",
        "url": "106k/105856/164146661/105856_3429_IMG_07_0000.jpeg",
        "caption": null
      },
      {
        "srcUrl": "https://media.rightmove.co.uk:443/dir/crop/10:9-16:9/106k/105856/164146661/105856_3429_IMG_08_0000_max_476x317.jpeg",
        "url": "106k/105856/164146661/105856_3429_IMG_08_0000.jpeg",
        "caption": null
      },
      {
        "srcUrl": "https://media.rightmove.co.uk:443/dir/crop/10:9-16:9/106k/105856/164146661/105856_3429_IMG_09_0000_max_476x317.jpeg",
        "url": "106k/105856/164146661/105856_3429_IMG_09_0000.jpeg",
        "caption": null
      }
    ],
    "propertySubType": "Apartment",
    "tenure": {
      "tenureType": null
    },
    "letAvailableDate": "2025-09-14T00:00:00Z",
    "listingUpdate": {
      "listingUpdateReason": "price_reduced",
      "listingUpdateDate": "2025-07-10T14:52:17Z"
    },
    "price": {
      "amount": 720,
      "frequency": "weekly",
      "currencyCode": "GBP",
      "displayPrices": [
        {
          "displayPrice": "£3,120 pcm",
          "displayPriceQualifier": ""
        },
        {
          "displayPrice": "£720 pw",
          "displayPriceQualifier": ""
        }
      ]
    },
    "premiumListing": false,
    "featuredProperty": true,
    "customer": {
      "branchId": 105856,
      "brandPlusLogoURI": "/brand/brand_logo_45523_0001.png",
      "contactTelephone": "020 3834 8384",
      "branchDisplayName": "Residential Realtors, London",
      "branchName": "London",
      "brandTradingName": "Residential Realtors",
      "branchLandingPageUrl": "/estate-agents/agent/Residential-Realtors/London-105856.html",
      "development": false,
      "mediaServerUrl": "https://media.rightmove.co.uk:443",
      "showReducedProperties": true,
      "hasBrandPlus": true,
      "commercial": false,
      "showOnMap": true,
      "enhancedListing": false,
      "developmentContent": null,
      "buildToRent": false,
      "buildToRentBenefits": [],
      "updateDate": "2025-05-29T09:23:47Z",
      "brandPlusLogoUrl": "https://media.rightmove.co.uk:443/brand/brand_logo_45523_0001.png"
    },
    "distance": 0.4256,
    "transactionType": "rent",
    "productLabel": {
      "productLabelText": null,
      "spotlightLabel": false
    },
    "commercial": false,
    "development": false,
    "residential": true,
    "students": true,
    "auction": false,
    "feesApply": true,
    "feesApplyText": "No Agency Fees",
    "displaySize": "",
    "showOnMap": true,
    "propertyUrl": "/properties/164146661#/?channel=RES_LET",
    "contactUrl": "/property-to-rent/contactBranch.html?propertyId=164146661",
    "staticMapUrl": null,
    "channel": "RENT",
    "firstVisibleDate": "2025-07-04T02:32:49Z",
    "keywords": [],
    "keywordMatchType": "no_keyword",
    "saved": false,
    "hidden": false,
    "onlineViewingsAvailable": false,
    "lozengeModel": {
      "matchingLozenges": []
    },
    "streetView": {
      "showStreetView": true
    },
    "enquiredTimestamp": null,
    "updateDate": "2025-07-10T14:52:20Z",
    "enquiryAddedTimestamp": null,
    "enquiryCalledTimestamp": null,
    "enhancedListing": false,
    "propertyImages": {
      "images": [
        {
          "srcUrl": "https://media.rightmove.co.uk:443/dir/crop/10:9-16:9/106k/105856/164146661/105856_3429_IMG_00_0000_max_476x317.jpeg",
          "url": "106k/105856/164146661/105856_3429_IMG_00_0000.jpeg",
          "caption": null
        },
        {
          "srcUrl": "https://media.rightmove.co.uk:443/dir/crop/10:9-16:9/106k/105856/164146661/105856_3429_IMG_01_0000_max_476x317.jpeg",
          "url": "106k/105856/164146661/105856_3429_IMG_01_0000.jpeg",
          "caption": null
        },
        {
          "srcUrl": "https://media.rightmove.co.uk:443/dir/crop/10:9-16:9/106k/105856/164146661/105856_3429_IMG_02_0000_max_476x317.jpeg",
          "url": "106k/105856/164146661/105856_3429_IMG_02_0000.jpeg",
          "caption": null
        },
        {
          "srcUrl": "https://media.rightmove.co.uk:443/dir/crop/10:9-16:9/106k/105856/164146661/105856_3429_IMG_03_0000_max_476x317.jpeg",
          "url": "106k/105856/164146661/105856_3429_IMG_03_0000.jpeg",
          "caption": null
        },
        {
          "srcUrl": "https://media.rightmove.co.uk:443/dir/crop/10:9-16:9/106k/105856/164146661/105856_3429_IMG_04_0000_max_476x317.jpeg",
          "url": "106k/105856/164146661/105856_3429_IMG_04_0000.jpeg",
          "caption": null
        },
        {
          "srcUrl": "https://media.rightmove.co.uk:443/dir/crop/10:9-16:9/106k/105856/164146661/105856_3429_IMG_05_0000_max_476x317.jpeg",
          "url": "106k/105856/164146661/105856_3429_IMG_05_0000.jpeg",
          "caption": null
        },
        {
          "srcUrl": "https://media.rightmove.co.uk:443/dir/crop/10:9-16:9/106k/105856/164146661/105856_3429_IMG_06_0000_max_476x317.jpeg",
          "url": "106k/105856/164146661/105856_3429_IMG_06_0000.jpeg",
          "caption": null
        },
        {
          "srcUrl": "https://media.rightmove.co.uk:443/dir/crop/10:9-16:9/106k/105856/164146661/105856_3429_IMG_07_0000_max_476x317.jpeg",
          "url": "106k/105856/164146661/105856_3429_IMG_07_0000.jpeg",
          "caption": null
        },
        {
          "srcUrl": "https://media.rightmove.co.uk:443/dir/crop/10:9-16:9/106k/105856/164146661/105856_3429_IMG_08_0000_max_476x317.jpeg",
          "url": "106k/105856/164146661/105856_3429_IMG_08_0000.jpeg",
          "caption": null
        },
        {
          "srcUrl": "https://media.rightmove.co.uk:443/dir/crop/10:9-16:9/106k/105856/164146661/105856_3429_IMG_09_0000_max_476x317.jpeg",
          "url": "106k/105856/164146661/105856_3429_IMG_09_0000.jpeg",
          "caption": null
        }
      ],
      "mainImageSrc": "https://media.rightmove.co.uk:443/dir/crop/10:9-16:9/106k/105856/164146661/105856_3429_IMG_00_0000_max_476x317.jpeg",
      "mainMapImageSrc": "https://media.rightmove.co.uk:443/dir/crop/10:9-16:9/106k/105856/164146661/105856_3429_IMG_00_0000_max_296x197.jpeg"
    },
    "formattedBranchName": " by Residential Realtors, London",
    "addedOrReduced": "Reduced on 10/07/2025",
    "formattedDistance": "0.43 miles",
    "heading": "Featured Property",
    "propertyTypeFullDescription": "3 bedroom apartment",
    "displayStatus": "",
    "isRecent": false,
    "hasBrandPlus": true
  },
  {
    "id": 164306795,
    "bedrooms": 3,
    "bathrooms": 3,
    "numberOfImages": 18,
    "numberOfFloorplans": 1,
    "numberOfVirtualTours": 0,
    "summary": "Looking for a phenomenal Three Bedroom apartment in the heart of SE1? Then look no further as this property may just be the right property for you! Call our Southbank Office to arrange a viewing today! ",
    "displayAddress": "Lapwing Court, 6 Swan Street, Borough, London, SE1",
    "countryCode": "GB",
    "location": {
      "latitude": 51.500352,
      "longitude": -0.093362
    },
    "images": [
      {
        "srcUrl": "https://media.rightmove.co.uk:443/dir/crop/10:9-16:9/108k/107902/164306795/107902_SBA160028_L_IMG_00_0000_max_476x317.jpeg",
        "url": "108k/107902/164306795/107902_SBA160028_L_IMG_00_0000.jpeg",
        "caption": "Photo 1"
      },
      {
        "srcUrl": "https://media.rightmove.co.uk:443/dir/crop/10:9-16:9/108k/107902/164306795/107902_SBA160028_L_IMG_01_0000_max_476x317.jpeg",
        "url": "108k/107902/164306795/107902_SBA160028_L_IMG_01_0000.jpeg",
        "caption": "Photo 2"
      },
      {
        "srcUrl": "https://media.rightmove.co.uk:443/dir/crop/10:9-16:9/108k/107902/164306795/107902_SBA160028_L_IMG_02_0000_max_476x317.jpeg",
        "url": "108k/107902/164306795/107902_SBA160028_L_IMG_02_0000.jpeg",
        "caption": "Photo 3"
      },
      {
        "srcUrl": "https://media.rightmove.co.uk:443/dir/crop/10:9-16:9/108k/107902/164306795/107902_SBA160028_L_IMG_03_0000_max_476x317.jpeg",
        "url": "108k/107902/164306795/107902_SBA160028_L_IMG_03_0000.jpeg",
        "caption": "Photo 4"
      },
      {
        "srcUrl": "https://media.rightmove.co.uk:443/dir/crop/10:9-16:9/108k/107902/164306795/107902_SBA160028_L_IMG_04_0000_max_476x317.jpeg",
        "url": "108k/107902/164306795/107902_SBA160028_L_IMG_04_0000.jpeg",
        "caption": "Photo 5"
      },
      {
        "srcUrl": "https://media.rightmove.co.uk:443/dir/crop/10:9-16:9/108k/107902/164306795/107902_SBA160028_L_IMG_05_0000_max_476x317.jpeg",
        "url": "108k/107902/164306795/107902_SBA160028_L_IMG_05_0000.jpeg",
        "caption": "Photo 6"
      },
      {
        "srcUrl": "https://media.rightmove.co.uk:443/dir/crop/10:9-16:9/108k/107902/164306795/107902_SBA160028_L_IMG_06_0000_max_476x317.jpeg",
        "url": "108k/107902/164306795/107902_SBA160028_L_IMG_06_0000.jpeg",
        "caption": "Photo 16"
      },
      {
        "srcUrl": "https://media.rightmove.co.uk:443/dir/crop/10:9-16:9/108k/107902/164306795/107902_SBA160028_L_IMG_07_0000_max_476x317.jpeg",
        "url": "108k/107902/164306795/107902_SBA160028_L_IMG_07_0000.jpeg",
        "caption": "Photo 7"
      },
      {
        "srcUrl": "https://media.rightmove.co.uk:443/dir/crop/10:9-16:9/108k/107902/164306795/107902_SBA160028_L_IMG_08_0000_max_476x317.jpeg",
        "url": "108k/107902/164306795/107902_SBA160028_L_IMG_08_0000.jpeg",
        "caption": "Photo 8"
      },
      {
        "srcUrl": "https://media.rightmove.co.uk:443/dir/crop/10:9-16:9/108k/107902/164306795/107902_SBA160028_L_IMG_09_0000_max_476x317.jpeg",
        "url": "108k/107902/164306795/107902_SBA160028_L_IMG_09_0000.jpeg",
        "caption": "Photo 9"
      },
      {
        "srcUrl": "https://media.rightmove.co.uk:443/dir/crop/10:9-16:9/108k/107902/164306795/107902_SBA160028_L_IMG_10_0000_max_476x317.jpeg",
        "url": "108k/107902/164306795/107902_SBA160028_L_IMG_10_0000.jpeg",
        "caption": "Photo 10"
      },
      {
        "srcUrl": "https://media.rightmove.co.uk:443/dir/crop/10:9-16:9/108k/107902/164306795/107902_SBA160028_L_IMG_11_0000_max_476x317.jpeg",
        "url": "108k/107902/164306795/107902_SBA160028_L_IMG_11_0000.jpeg",
        "caption": "Photo 11"
      },
      {
        "srcUrl": "https://media.rightmove.co.uk:443/dir/crop/10:9-16:9/108k/107902/164306795/107902_SBA160028_L_IMG_12_0000_max_476x317.jpeg",
        "url": "108k/107902/164306795/107902_SBA160028_L_IMG_12_0000.jpeg",
        "caption": "Photo 12"
      },
      {
        "srcUrl": "https://media.rightmove.co.uk:443/dir/crop/10:9-16:9/108k/107902/164306795/107902_SBA160028_L_IMG_13_0000_max_476x317.jpeg",
        "url": "108k/107902/164306795/107902_SBA160028_L_IMG_13_0000.jpeg",
        "caption": "Photo 13"
      },
      {
        "srcUrl": "https://media.rightmove.co.uk:443/dir/crop/10:9-16:9/108k/107902/164306795/107902_SBA160028_L_IMG_14_0000_max_476x317.jpeg",
        "url": "108k/107902/164306795/107902_SBA160028_L_IMG_14_0000.jpeg",
        "caption": "Photo 14"
      },
      {
        "srcUrl": "https://media.rightmove.co.uk:443/dir/crop/10:9-16:9/108k/107902/164306795/107902_SBA160028_L_IMG_15_0000_max_476x317.jpeg",
        "url": "108k/107902/164306795/107902_SBA160028_L_IMG_15_0000.jpeg",
        "caption": "Photo 15"
      },
      {
        "srcUrl": "https://media.rightmove.co.uk:443/dir/crop/10:9-16:9/108k/107902/164306795/107902_SBA160028_L_IMG_16_0000_max_476x317.jpeg",
        "url": "108k/107902/164306795/107902_SBA160028_L_IMG_16_0000.jpeg",
        "caption": "Photo 17"
      },
      {
        "srcUrl": "https://media.rightmove.co.uk:443/dir/crop/10:9-16:9/108k/107902/164306795/107902_SBA160028_L_IMG_17_0000_max_476x317.jpeg",
        "url": "108k/107902/164306795/107902_SBA160028_L_IMG_17_0000.jpeg",
        "caption": "Photo 18"
      }
    ],
    "propertySubType": "Apartment",
    "tenure": {
      "tenureType": null
    },
    "letAvailableDate": "2025-09-16T00:00:00Z",
    "listingUpdate": {
      "listingUpdateReason": "price_reduced",
      "listingUpdateDate": "2025-07-14T14:15:14Z"
    },
    "price": {
      "amount": 3500,
      "frequency": "monthly",
      "currencyCode": "GBP",
      "displayPrices": [
        {
          "displayPrice": "£3,500 pcm",
          "displayPriceQualifier": ""
        },
        {
          "displayPrice": "£808 pw",
          "displayPriceQualifier": ""
        }
      ]
    },
    "premiumListing": false,
    "featuredProperty": false,
    "customer": {
      "branchId": 107902,
      "brandPlusLogoURI": "/108k/107902/branch_rmchoice_logo_107902_0000.jpeg",
      "contactTelephone": "020 7620 1600",
      "branchDisplayName": "Life Residential, County Hall - South Bank Lettings",
      "branchName": "County Hall - South Bank Lettings",
      "brandTradingName": "Life Residential",
      "branchLandingPageUrl": "/estate-agents/agent/Life-Residential/County-Hall---South-Bank-Lettings-107902.html",
      "development": false,
      "mediaServerUrl": "https://media.rightmove.co.uk:443",
      "showReducedProperties": true,
      "hasBrandPlus": true,
      "commercial": false,
      "showOnMap": true,
      "enhancedListing": false,
      "developmentContent": null,
      "buildToRent": false,
      "buildToRentBenefits": [],
      "updateDate": "2025-06-25T16:18:12Z",
      "brandPlusLogoUrl": "https://media.rightmove.co.uk:443/108k/107902/branch_rmchoice_logo_107902_0000.jpeg"
    },
    "distance": 0.4502,
    "transactionType": "rent",
    "productLabel": {
      "productLabelText": null,
      "spotlightLabel": false
    },
    "commercial": false,
    "development": false,
    "residential": true,
    "students": false,
    "auction": false,
    "feesApply": true,
    "feesApplyText": null,
    "displaySize": "838 sq. ft.",
    "showOnMap": true,
    "propertyUrl": "/properties/164306795#/?channel=RES_LET",
    "contactUrl": "/property-to-rent/contactBranch.html?propertyId=164306795",
    "staticMapUrl": null,
    "channel": "RENT",
    "firstVisibleDate": "2025-07-08T14:25:07Z",
    "keywords": [],
    "keywordMatchType": "no_keyword",
    "saved": false,
    "hidden": false,
    "onlineViewingsAvailable": false,
    "lozengeModel": {
      "matchingLozenges": []
    },
    "streetView": {
      "showStreetView": true
    },
    "enquiredTimestamp": null,
    "updateDate": "2025-07-14T14:15:15Z",
    "enquiryAddedTimestamp": null,
    "enquiryCalledTimestamp": null,
    "enhancedListing": false,
    "propertyImages": {
      "images": [
        {
          "srcUrl": "https://media.rightmove.co.uk:443/dir/crop/10:9-16:9/108k/107902/164306795/107902_SBA160028_L_IMG_00_0000_max_476x317.jpeg",
          "url": "108k/107902/164306795/107902_SBA160028_L_IMG_00_0000.jpeg",
          "caption": "Photo 1"
        },
        {
          "srcUrl": "https://media.rightmove.co.uk:443/dir/crop/10:9-16:9/108k/107902/164306795/107902_SBA160028_L_IMG_01_0000_max_476x317.jpeg",
          "url": "108k/107902/164306795/107902_SBA160028_L_IMG_01_0000.jpeg",
          "caption": "Photo 2"
        },
        {
          "srcUrl": "https://media.rightmove.co.uk:443/dir/crop/10:9-16:9/108k/107902/164306795/107902_SBA160028_L_IMG_02_0000_max_476x317.jpeg",
          "url": "108k/107902/164306795/107902_SBA160028_L_IMG_02_0000.jpeg",
          "caption": "Photo 3"
        },
        {
          "srcUrl": "https://media.rightmove.co.uk:443/dir/crop/10:9-16:9/108k/107902/164306795/107902_SBA160028_L_IMG_03_0000_max_476x317.jpeg",
          "url": "108k/107902/164306795/107902_SBA160028_L_IMG_03_0000.jpeg",
          "caption": "Photo 4"
        },
        {
          "srcUrl": "https://media.rightmove.co.uk:443/dir/crop/10:9-16:9/108k/107902/164306795/107902_SBA160028_L_IMG_04_0000_max_476x317.jpeg",
          "url": "108k/107902/164306795/107902_SBA160028_L_IMG_04_0000.jpeg",
          "caption": "Photo 5"
        },
        {
          "srcUrl": "https://media.rightmove.co.uk:443/dir/crop/10:9-16:9/108k/107902/164306795/107902_SBA160028_L_IMG_05_0000_max_476x317.jpeg",
          "url": "108k/107902/164306795/107902_SBA160028_L_IMG_05_0000.jpeg",
          "caption": "Photo 6"
        },
        {
          "srcUrl": "https://media.rightmove.co.uk:443/dir/crop/10:9-16:9/108k/107902/164306795/107902_SBA160028_L_IMG_06_0000_max_476x317.jpeg",
          "url": "108k/107902/164306795/107902_SBA160028_L_IMG_06_0000.jpeg",
          "caption": "Photo 16"
        },
        {
          "srcUrl": "https://media.rightmove.co.uk:443/dir/crop/10:9-16:9/108k/107902/164306795/107902_SBA160028_L_IMG_07_0000_max_476x317.jpeg",
          "url": "108k/107902/164306795/107902_SBA160028_L_IMG_07_0000.jpeg",
          "caption": "Photo 7"
        },
        {
          "srcUrl": "https://media.rightmove.co.uk:443/dir/crop/10:9-16:9/108k/107902/164306795/107902_SBA160028_L_IMG_08_0000_max_476x317.jpeg",
          "url": "108k/107902/164306795/107902_SBA160028_L_IMG_08_0000.jpeg",
          "caption": "Photo 8"
        },
        {
          "srcUrl": "https://media.rightmove.co.uk:443/dir/crop/10:9-16:9/108k/107902/164306795/107902_SBA160028_L_IMG_09_0000_max_476x317.jpeg",
          "url": "108k/107902/164306795/107902_SBA160028_L_IMG_09_0000.jpeg",
          "caption": "Photo 9"
        },
        {
          "srcUrl": "https://media.rightmove.co.uk:443/dir/crop/10:9-16:9/108k/107902/164306795/107902_SBA160028_L_IMG_10_0000_max_476x317.jpeg",
          "url": "108k/107902/164306795/107902_SBA160028_L_IMG_10_0000.jpeg",
          "caption": "Photo 10"
        },
        {
          "srcUrl": "https://media.rightmove.co.uk:443/dir/crop/10:9-16:9/108k/107902/164306795/107902_SBA160028_L_IMG_11_0000_max_476x317.jpeg",
          "url": "108k/107902/164306795/107902_SBA160028_L_IMG_11_0000.jpeg",
          "caption": "Photo 11"
        },
        {
          "srcUrl": "https://media.rightmove.co.uk:443/dir/crop/10:9-16:9/108k/107902/164306795/107902_SBA160028_L_IMG_12_0000_max_476x317.jpeg",
          "url": "108k/107902/164306795/107902_SBA160028_L_IMG_12_0000.jpeg",
          "caption": "Photo 12"
        },
        {
          "srcUrl": "https://media.rightmove.co.uk:443/dir/crop/10:9-16:9/108k/107902/164306795/107902_SBA160028_L_IMG_13_0000_max_476x317.jpeg",
          "url": "108k/107902/164306795/107902_SBA160028_L_IMG_13_0000.jpeg",
          "caption": "Photo 13"
        },
        {
          "srcUrl": "https://media.rightmove.co.uk:443/dir/crop/10:9-16:9/108k/107902/164306795/107902_SBA160028_L_IMG_14_0000_max_476x317.jpeg",
          "url": "108k/107902/164306795/107902_SBA160028_L_IMG_14_0000.jpeg",
          "caption": "Photo 14"
        },
        {
          "srcUrl": "https://media.rightmove.co.uk:443/dir/crop/10:9-16:9/108k/107902/164306795/107902_SBA160028_L_IMG_15_0000_max_476x317.jpeg",
          "url": "108k/107902/164306795/107902_SBA160028_L_IMG_15_0000.jpeg",
          "caption": "Photo 15"
        },
        {
          "srcUrl": "https://media.rightmove.co.uk:443/dir/crop/10:9-16:9/108k/107902/164306795/107902_SBA160028_L_IMG_16_0000_max_476x317.jpeg",
          "url": "108k/107902/164306795/107902_SBA160028_L_IMG_16_0000.jpeg",
          "caption": "Photo 17"
        },
        {
          "srcUrl": "https://media.rightmove.co.uk:443/dir/crop/10:9-16:9/108k/107902/164306795/107902_SBA160028_L_IMG_17_0000_max_476x317.jpeg",
          "url": "108k/107902/164306795/107902_SBA160028_L_IMG_17_0000.jpeg",
          "caption": "Photo 18"
        }
      ],
      "mainImageSrc": "https://media.rightmove.co.uk:443/dir/crop/10:9-16:9/108k/107902/164306795/107902_SBA160028_L_IMG_00_0000_max_476x317.jpeg",
      "mainMapImageSrc": "https://media.rightmove.co.uk:443/dir/crop/10:9-16:9/108k/107902/164306795/107902_SBA160028_L_IMG_00_0000_max_296x197.jpeg"
    },
    "formattedBranchName": " by Life Residential, County Hall - South Bank Lettings",
    "addedOrReduced": "Reduced yesterday",
    "formattedDistance": "0.45 miles",
    "heading": "",
    "propertyTypeFullDescription": "3 bedroom apartment",
    "displayStatus": "",
    "isRecent": true,
    "hasBrandPlus": true
  },
  {
    "id": 87183936,
    "bedrooms": 3,
    "bathrooms": 2,
    "numberOfImages": 19,
    "numberOfFloorplans": 1,
    "numberOfVirtualTours": 1,
    "summary": "No Deposit Option Available For Tenants. A three bedroom, two bathroom apartment situated in a secure development in the heart of SE1. This property comprises of a kitchen with integrated appliances, wood floors, and good-sized bedrooms. Providing easy access into the City ...",
    "displayAddress": "Swan Street, London, SE1",
    "countryCode": "GB",
    "location": {
      "latitude": 51.500005,
      "longitude": -0.092866
    },
    "images": [
      {
        "srcUrl": "https://media.rightmove.co.uk:443/dir/crop/10:9-16:9/78k/77508/87183936/77508_LBL240048_L_IMG_00_0000_max_476x317.jpeg",
        "url": "78k/77508/87183936/77508_LBL240048_L_IMG_00_0000.jpeg",
        "caption": "Living Room"
      },
      {
        "srcUrl": "https://media.rightmove.co.uk:443/dir/crop/10:9-16:9/78k/77508/87183936/77508_LBL240048_L_IMG_01_0000_max_476x317.jpeg",
        "url": "78k/77508/87183936/77508_LBL240048_L_IMG_01_0000.jpeg",
        "caption": "Kitchen"
      },
      {
        "srcUrl": "https://media.rightmove.co.uk:443/dir/crop/10:9-16:9/78k/77508/87183936/77508_LBL240048_L_IMG_02_0000_max_476x317.jpeg",
        "url": "78k/77508/87183936/77508_LBL240048_L_IMG_02_0000.jpeg",
        "caption": "Bedroom"
      },
      {
        "srcUrl": "https://media.rightmove.co.uk:443/dir/crop/10:9-16:9/78k/77508/87183936/77508_LBL240048_L_IMG_03_0000_max_476x317.jpeg",
        "url": "78k/77508/87183936/77508_LBL240048_L_IMG_03_0000.jpeg",
        "caption": "Bathroom"
      },
      {
        "srcUrl": "https://media.rightmove.co.uk:443/dir/crop/10:9-16:9/78k/77508/87183936/77508_LBL240048_L_IMG_04_0000_max_476x317.jpeg",
        "url": "78k/77508/87183936/77508_LBL240048_L_IMG_04_0000.jpeg",
        "caption": "Exterior"
      },
      {
        "srcUrl": "https://media.rightmove.co.uk:443/dir/crop/10:9-16:9/78k/77508/87183936/77508_LBL240048_L_IMG_05_0000_max_476x317.jpeg",
        "url": "78k/77508/87183936/77508_LBL240048_L_IMG_05_0000.jpeg",
        "caption": "Living Room"
      },
      {
        "srcUrl": "https://media.rightmove.co.uk:443/dir/crop/10:9-16:9/78k/77508/87183936/77508_LBL240048_L_IMG_06_0000_max_476x317.jpeg",
        "url": "78k/77508/87183936/77508_LBL240048_L_IMG_06_0000.jpeg",
        "caption": "Living Room"
      },
      {
        "srcUrl": "https://media.rightmove.co.uk:443/dir/crop/10:9-16:9/78k/77508/87183936/77508_LBL240048_L_IMG_07_0000_max_476x317.jpeg",
        "url": "78k/77508/87183936/77508_LBL240048_L_IMG_07_0000.jpeg",
        "caption": "Kitchen/Living Room"
      },
      {
        "srcUrl": "https://media.rightmove.co.uk:443/dir/crop/10:9-16:9/78k/77508/87183936/77508_LBL240048_L_IMG_08_0000_max_476x317.jpeg",
        "url": "78k/77508/87183936/77508_LBL240048_L_IMG_08_0000.jpeg",
        "caption": "Kitchen/Living Room"
      },
      {
        "srcUrl": "https://media.rightmove.co.uk:443/dir/crop/10:9-16:9/78k/77508/87183936/77508_LBL240048_L_IMG_09_0000_max_476x317.jpeg",
        "url": "78k/77508/87183936/77508_LBL240048_L_IMG_09_0000.jpeg",
        "caption": "Kitchen"
      },
      {
        "srcUrl": "https://media.rightmove.co.uk:443/dir/crop/10:9-16:9/78k/77508/87183936/77508_LBL240048_L_IMG_10_0000_max_476x317.jpeg",
        "url": "78k/77508/87183936/77508_LBL240048_L_IMG_10_0000.jpeg",
        "caption": "Bedroom"
      },
      {
        "srcUrl": "https://media.rightmove.co.uk:443/dir/crop/10:9-16:9/78k/77508/87183936/77508_LBL240048_L_IMG_11_0000_max_476x317.jpeg",
        "url": "78k/77508/87183936/77508_LBL240048_L_IMG_11_0000.jpeg",
        "caption": "Bedroom"
      },
      {
        "srcUrl": "https://media.rightmove.co.uk:443/dir/crop/10:9-16:9/78k/77508/87183936/77508_LBL240048_L_IMG_12_0000_max_476x317.jpeg",
        "url": "78k/77508/87183936/77508_LBL240048_L_IMG_12_0000.jpeg",
        "caption": "Bedroom"
      },
      {
        "srcUrl": "https://media.rightmove.co.uk:443/dir/crop/10:9-16:9/78k/77508/87183936/77508_LBL240048_L_IMG_13_0000_max_476x317.jpeg",
        "url": "78k/77508/87183936/77508_LBL240048_L_IMG_13_0000.jpeg",
        "caption": "Bedroom"
      },
      {
        "srcUrl": "https://media.rightmove.co.uk:443/dir/crop/10:9-16:9/78k/77508/87183936/77508_LBL240048_L_IMG_14_0000_max_476x317.jpeg",
        "url": "78k/77508/87183936/77508_LBL240048_L_IMG_14_0000.jpeg",
        "caption": "Bedroom/Bathroom"
      },
      {
        "srcUrl": "https://media.rightmove.co.uk:443/dir/crop/10:9-16:9/78k/77508/87183936/77508_LBL240048_L_IMG_15_0000_max_476x317.jpeg",
        "url": "78k/77508/87183936/77508_LBL240048_L_IMG_15_0000.jpeg",
        "caption": "Bathroom"
      },
      {
        "srcUrl": "https://media.rightmove.co.uk:443/dir/crop/10:9-16:9/78k/77508/87183936/77508_LBL240048_L_IMG_16_0000_max_476x317.jpeg",
        "url": "78k/77508/87183936/77508_LBL240048_L_IMG_16_0000.jpeg",
        "caption": "Hallway"
      },
      {
        "srcUrl": "https://media.rightmove.co.uk:443/dir/crop/10:9-16:9/78k/77508/87183936/77508_LBL240048_L_IMG_17_0000_max_476x317.jpeg",
        "url": "78k/77508/87183936/77508_LBL240048_L_IMG_17_0000.jpeg",
        "caption": "Window"
      },
      {
        "srcUrl": "https://media.rightmove.co.uk:443/dir/crop/10:9-16:9/78k/77508/87183936/77508_LBL240048_L_IMG_18_0000_max_476x317.jpeg",
        "url": "78k/77508/87183936/77508_LBL240048_L_IMG_18_0000.jpeg",
        "caption": "Exterior"
      }
    ],
    "propertySubType": "Apartment",
    "tenure": {
      "tenureType": null
    },
    "letAvailableDate": "2025-09-09T00:00:00Z",
    "listingUpdate": {
      "listingUpdateReason": "price_reduced",
      "listingUpdateDate": "2025-07-11T10:20:13Z"
    },
    "price": {
      "amount": 3250,
      "frequency": "monthly",
      "currencyCode": "GBP",
      "displayPrices": [
        {
          "displayPrice": "£3,250 pcm",
          "displayPriceQualifier": ""
        },
        {
          "displayPrice": "£750 pw",
          "displayPriceQualifier": ""
        }
      ]
    },
    "premiumListing": false,
    "featuredProperty": false,
    "customer": {
      "branchId": 77508,
      "brandPlusLogoURI": "/brand/brand_rmchoice_logo_104024_0000.jpeg",
      "contactTelephone": "020 3834 8152",
      "branchDisplayName": "Stirling Ackroyd Lettings, London Bridge",
      "branchName": "London Bridge",
      "brandTradingName": "Stirling Ackroyd Lettings",
      "branchLandingPageUrl": "/estate-agents/agent/Stirling-Ackroyd-Lettings/London-Bridge-77508.html",
      "development": false,
      "mediaServerUrl": "https://media.rightmove.co.uk:443",
      "showReducedProperties": true,
      "hasBrandPlus": true,
      "commercial": false,
      "showOnMap": true,
      "enhancedListing": false,
      "developmentContent": null,
      "buildToRent": false,
      "buildToRentBenefits": [],
      "updateDate": "2025-06-12T16:31:03Z",
      "brandPlusLogoUrl": "https://media.rightmove.co.uk:443/brand/brand_rmchoice_logo_104024_0000.jpeg"
    },
    "distance": 0.4536,
    "transactionType": "rent",
    "productLabel": {
      "productLabelText": null,
      "spotlightLabel": false
    },
    "commercial": false,
    "development": false,
    "residential": true,
    "students": false,
    "auction": false,
    "feesApply": true,
    "feesApplyText": "We are a member of Propertymark (which includes their Client Money Protection Scheme) and The Property Ombudsman. The information given below is provided to ensure you are fully informed of any fees and costs involved in renting a property. All fees & charges are shown inc VAT.<br /><br /> <b><u>Holding deposit (per tenancy):</u></b> <br /><br />One week s rent. Please Note: This will be withheld if any relevant person (including any guarantor(s)) withdraw from the tenancy, fail a Right-to-Rent check, provide materially significant false or misleading information, or fail to sign their tenancy agreement (and / or Deed of Guarantee) within 15 calendar days (or other Deadline for Agreement as mutually agreed in writing).<br /><br /> Security Deposit (per tenancy, Rent of less than £50,000 per year):Five weeks  rent. This covers damage or defaults on the part of the tenant during the tenancy.<br /><br /> Security Deposit (per tenancy, Rent of £50,000 or over per year):Six weeks  rent. This covers damages or defaults on the part of the tenant during the tenancy.<br /><br /> <b><u>Unpaid Rent:</u></b> <br /><br />\rInterest at 3% above the Bank of England Base Rate from Rent Due Date until paid in order to pursue non-payment of rent. Please note: This will not be levied until the rent is more than 14 days in arrears.<br /><br /> <b><u>Lost Key(s) or other Security Device(s):</u></b> <br /><br /> Tenants are liable for the actual cost of replacing any lost key(s) or other security device(s). If the loss results in locks needing to be changed, the actual costs of a locksmith, new lock and replacement keys for the tenant, landlord and any other persons requiring keys will be charged to the tenant.<br /><br /> <b><u>Variation of Contract (Tenant s Request):</u></b> <br /><br /> £50 (inc VAT) per agreed variation. To cover the costs associated with taking landlord s instructions as well as the preparation and execution of new legal documents.<br /><br /> <b><u>Change of sharer (Tenant s Request):</u></b> <br /><br />\r£50 (inc VAT) per replacement tenant or any reasonable costs incurred if higher. To cover the costs associated with taking landlord s instructions, new tenant referencing and Right-to-Rent checks, deposit registration as well as the preparation and execution.<br /><br /> <b><u>Early Termination (Tenant s Request):</u></b> <br /><br />Should the tenant wish to leave their contract early, they shall be liable to the landlord s costs in re-letting the property as well as all rent due under the tenancy until the start date of the replacement tenancy. These costs will be no more than the maximum amount of rent outstanding on the tenancy <br /><br /> <b><u>No Deposit Option:</u></b> <br /><br />\rOur No Deposit Option (NDO) is part of the Residency membership. With this option the tenant can pay the monthly membership fee and not need to have the traditional deposit amount tied up for the duration of the tenancy. The tenant will still be liable for any damages at the end of the tenancy. <br /><br />",
    "displaySize": "",
    "showOnMap": true,
    "propertyUrl": "/properties/87183936#/?channel=RES_LET",
    "contactUrl": "/property-to-rent/contactBranch.html?propertyId=87183936",
    "staticMapUrl": null,
    "channel": "RENT",
    "firstVisibleDate": "2025-07-10T10:45:30Z",
    "keywords": [],
    "keywordMatchType": "no_keyword",
    "saved": false,
    "hidden": false,
    "onlineViewingsAvailable": false,
    "lozengeModel": {
      "matchingLozenges": []
    },
    "streetView": {
      "showStreetView": true
    },
    "enquiredTimestamp": null,
    "updateDate": "2025-07-14T23:14:25Z",
    "enquiryAddedTimestamp": null,
    "enquiryCalledTimestamp": null,
    "enhancedListing": false,
    "propertyImages": {
      "images": [
        {
          "srcUrl": "https://media.rightmove.co.uk:443/dir/crop/10:9-16:9/78k/77508/87183936/77508_LBL240048_L_IMG_00_0000_max_476x317.jpeg",
          "url": "78k/77508/87183936/77508_LBL240048_L_IMG_00_0000.jpeg",
          "caption": "Living Room"
        },
        {
          "srcUrl": "https://media.rightmove.co.uk:443/dir/crop/10:9-16:9/78k/77508/87183936/77508_LBL240048_L_IMG_01_0000_max_476x317.jpeg",
          "url": "78k/77508/87183936/77508_LBL240048_L_IMG_01_0000.jpeg",
          "caption": "Kitchen"
        },
        {
          "srcUrl": "https://media.rightmove.co.uk:443/dir/crop/10:9-16:9/78k/77508/87183936/77508_LBL240048_L_IMG_02_0000_max_476x317.jpeg",
          "url": "78k/77508/87183936/77508_LBL240048_L_IMG_02_0000.jpeg",
          "caption": "Bedroom"
        },
        {
          "srcUrl": "https://media.rightmove.co.uk:443/dir/crop/10:9-16:9/78k/77508/87183936/77508_LBL240048_L_IMG_03_0000_max_476x317.jpeg",
          "url": "78k/77508/87183936/77508_LBL240048_L_IMG_03_0000.jpeg",
          "caption": "Bathroom"
        },
        {
          "srcUrl": "https://media.rightmove.co.uk:443/dir/crop/10:9-16:9/78k/77508/87183936/77508_LBL240048_L_IMG_04_0000_max_476x317.jpeg",
          "url": "78k/77508/87183936/77508_LBL240048_L_IMG_04_0000.jpeg",
          "caption": "Exterior"
        },
        {
          "srcUrl": "https://media.rightmove.co.uk:443/dir/crop/10:9-16:9/78k/77508/87183936/77508_LBL240048_L_IMG_05_0000_max_476x317.jpeg",
          "url": "78k/77508/87183936/77508_LBL240048_L_IMG_05_0000.jpeg",
          "caption": "Living Room"
        },
        {
          "srcUrl": "https://media.rightmove.co.uk:443/dir/crop/10:9-16:9/78k/77508/87183936/77508_LBL240048_L_IMG_06_0000_max_476x317.jpeg",
          "url": "78k/77508/87183936/77508_LBL240048_L_IMG_06_0000.jpeg",
          "caption": "Living Room"
        },
        {
          "srcUrl": "https://media.rightmove.co.uk:443/dir/crop/10:9-16:9/78k/77508/87183936/77508_LBL240048_L_IMG_07_0000_max_476x317.jpeg",
          "url": "78k/77508/87183936/77508_LBL240048_L_IMG_07_0000.jpeg",
          "caption": "Kitchen/Living Room"
        },
        {
          "srcUrl": "https://media.rightmove.co.uk:443/dir/crop/10:9-16:9/78k/77508/87183936/77508_LBL240048_L_IMG_08_0000_max_476x317.jpeg",
          "url": "78k/77508/87183936/77508_LBL240048_L_IMG_08_0000.jpeg",
          "caption": "Kitchen/Living Room"
        },
        {
          "srcUrl": "https://media.rightmove.co.uk:443/dir/crop/10:9-16:9/78k/77508/87183936/77508_LBL240048_L_IMG_09_0000_max_476x317.jpeg",
          "url": "78k/77508/87183936/77508_LBL240048_L_IMG_09_0000.jpeg",
          "caption": "Kitchen"
        },
        {
          "srcUrl": "https://media.rightmove.co.uk:443/dir/crop/10:9-16:9/78k/77508/87183936/77508_LBL240048_L_IMG_10_0000_max_476x317.jpeg",
          "url": "78k/77508/87183936/77508_LBL240048_L_IMG_10_0000.jpeg",
          "caption": "Bedroom"
        },
        {
          "srcUrl": "https://media.rightmove.co.uk:443/dir/crop/10:9-16:9/78k/77508/87183936/77508_LBL240048_L_IMG_11_0000_max_476x317.jpeg",
          "url": "78k/77508/87183936/77508_LBL240048_L_IMG_11_0000.jpeg",
          "caption": "Bedroom"
        },
        {
          "srcUrl": "https://media.rightmove.co.uk:443/dir/crop/10:9-16:9/78k/77508/87183936/77508_LBL240048_L_IMG_12_0000_max_476x317.jpeg",
          "url": "78k/77508/87183936/77508_LBL240048_L_IMG_12_0000.jpeg",
          "caption": "Bedroom"
        },
        {
          "srcUrl": "https://media.rightmove.co.uk:443/dir/crop/10:9-16:9/78k/77508/87183936/77508_LBL240048_L_IMG_13_0000_max_476x317.jpeg",
          "url": "78k/77508/87183936/77508_LBL240048_L_IMG_13_0000.jpeg",
          "caption": "Bedroom"
        },
        {
          "srcUrl": "https://media.rightmove.co.uk:443/dir/crop/10:9-16:9/78k/77508/87183936/77508_LBL240048_L_IMG_14_0000_max_476x317.jpeg",
          "url": "78k/77508/87183936/77508_LBL240048_L_IMG_14_0000.jpeg",
          "caption": "Bedroom/Bathroom"
        },
        {
          "srcUrl": "https://media.rightmove.co.uk:443/dir/crop/10:9-16:9/78k/77508/87183936/77508_LBL240048_L_IMG_15_0000_max_476x317.jpeg",
          "url": "78k/77508/87183936/77508_LBL240048_L_IMG_15_0000.jpeg",
          "caption": "Bathroom"
        },
        {
          "srcUrl": "https://media.rightmove.co.uk:443/dir/crop/10:9-16:9/78k/77508/87183936/77508_LBL240048_L_IMG_16_0000_max_476x317.jpeg",
          "url": "78k/77508/87183936/77508_LBL240048_L_IMG_16_0000.jpeg",
          "caption": "Hallway"
        },
        {
          "srcUrl": "https://media.rightmove.co.uk:443/dir/crop/10:9-16:9/78k/77508/87183936/77508_LBL240048_L_IMG_17_0000_max_476x317.jpeg",
          "url": "78k/77508/87183936/77508_LBL240048_L_IMG_17_0000.jpeg",
          "caption": "Window"
        },
        {
          "srcUrl": "https://media.rightmove.co.uk:443/dir/crop/10:9-16:9/78k/77508/87183936/77508_LBL240048_L_IMG_18_0000_max_476x317.jpeg",
          "url": "78k/77508/87183936/77508_LBL240048_L_IMG_18_0000.jpeg",
          "caption": "Exterior"
        }
      ],
      "mainImageSrc": "https://media.rightmove.co.uk:443/dir/crop/10:9-16:9/78k/77508/87183936/77508_LBL240048_L_IMG_00_0000_max_476x317.jpeg",
      "mainMapImageSrc": "https://media.rightmove.co.uk:443/dir/crop/10:9-16:9/78k/77508/87183936/77508_LBL240048_L_IMG_00_0000_max_296x197.jpeg"
    },
    "formattedBranchName": " by Stirling Ackroyd Lettings, London Bridge",
    "addedOrReduced": "Reduced on 11/07/2025",
    "formattedDistance": "0.45 miles",
    "heading": "",
    "propertyTypeFullDescription": "3 bedroom apartment",
    "displayStatus": "",
    "isRecent": false,
    "hasBrandPlus": true
  },
  {
    "id": 87215262,
    "bedrooms": 3,
    "bathrooms": 1,
    "numberOfImages": 5,
    "numberOfFloorplans": 1,
    "numberOfVirtualTours": 0,
    "summary": "***PRE VIEWING RESERVATION AVAILABLE, READ DESCRIPTION FOR FURTHER DETAILS***",
    "displayAddress": "Crayford House, Tabard Garden Estate, London, SE1",
    "countryCode": "GB",
    "location": {
      "latitude": 51.499237,
      "longitude": -0.087283
    },
    "images": [
      {
        "srcUrl": "https://media.rightmove.co.uk:443/dir/crop/10:9-16:9/106k/105856/87215262/105856_3500_IMG_00_0000_max_476x317.jpeg",
        "url": "106k/105856/87215262/105856_3500_IMG_00_0000.jpeg",
        "caption": null
      },
      {
        "srcUrl": "https://media.rightmove.co.uk:443/dir/crop/10:9-16:9/106k/105856/87215262/105856_3500_IMG_01_0000_max_476x317.jpeg",
        "url": "106k/105856/87215262/105856_3500_IMG_01_0000.jpeg",
        "caption": null
      },
      {
        "srcUrl": "https://media.rightmove.co.uk:443/dir/crop/10:9-16:9/106k/105856/87215262/105856_3500_IMG_02_0000_max_476x317.jpeg",
        "url": "106k/105856/87215262/105856_3500_IMG_02_0000.jpeg",
        "caption": null
      },
      {
        "srcUrl": "https://media.rightmove.co.uk:443/dir/crop/10:9-16:9/106k/105856/87215262/105856_3500_IMG_03_0000_max_476x317.jpeg",
        "url": "106k/105856/87215262/105856_3500_IMG_03_0000.jpeg",
        "caption": null
      },
      {
        "srcUrl": "https://media.rightmove.co.uk:443/dir/crop/10:9-16:9/106k/105856/87215262/105856_3500_IMG_04_0000_max_476x317.jpeg",
        "url": "106k/105856/87215262/105856_3500_IMG_04_0000.jpeg",
        "caption": null
      }
    ],
    "propertySubType": "Flat",
    "tenure": {
      "tenureType": null
    },
    "letAvailableDate": "2025-08-10T00:00:00Z",
    "listingUpdate": {
      "listingUpdateReason": "new",
      "listingUpdateDate": "2025-07-10T16:01:10Z"
    },
    "price": {
      "amount": 700,
      "frequency": "weekly",
      "currencyCode": "GBP",
      "displayPrices": [
        {
          "displayPrice": "£3,033 pcm",
          "displayPriceQualifier": ""
        },
        {
          "displayPrice": "£700 pw",
          "displayPriceQualifier": ""
        }
      ]
    },
    "premiumListing": false,
    "featuredProperty": false,
    "customer": {
      "branchId": 105856,
      "brandPlusLogoURI": "/brand/brand_logo_45523_0001.png",
      "contactTelephone": "020 3834 8384",
      "branchDisplayName": "Residential Realtors, London",
      "branchName": "London",
      "brandTradingName": "Residential Realtors",
      "branchLandingPageUrl": "/estate-agents/agent/Residential-Realtors/London-105856.html",
      "development": false,
      "mediaServerUrl": "https://media.rightmove.co.uk:443",
      "showReducedProperties": true,
      "hasBrandPlus": true,
      "commercial": false,
      "showOnMap": true,
      "enhancedListing": false,
      "developmentContent": null,
      "buildToRent": false,
      "buildToRentBenefits": [],
      "updateDate": "2025-05-29T09:23:47Z",
      "brandPlusLogoUrl": "https://media.rightmove.co.uk:443/brand/brand_logo_45523_0001.png"
    },
    "distance": 0.4032,
    "transactionType": "rent",
    "productLabel": {
      "productLabelText": null,
      "spotlightLabel": false
    },
    "commercial": false,
    "development": false,
    "residential": true,
    "students": false,
    "auction": false,
    "feesApply": true,
    "feesApplyText": "No Agency Fees",
    "displaySize": "",
    "showOnMap": true,
    "propertyUrl": "/properties/87215262#/?channel=RES_LET",
    "contactUrl": "/property-to-rent/contactBranch.html?propertyId=87215262",
    "staticMapUrl": null,
    "channel": "RENT",
    "firstVisibleDate": "2025-07-10T15:55:29Z",
    "keywords": [],
    "keywordMatchType": "no_keyword",
    "saved": false,
    "hidden": false,
    "onlineViewingsAvailable": false,
    "lozengeModel": {
      "matchingLozenges": []
    },
    "streetView": {
      "showStreetView": true
    },
    "enquiredTimestamp": null,
    "updateDate": "2025-07-10T16:01:10Z",
    "enquiryAddedTimestamp": null,
    "enquiryCalledTimestamp": null,
    "enhancedListing": false,
    "propertyImages": {
      "images": [
        {
          "srcUrl": "https://media.rightmove.co.uk:443/dir/crop/10:9-16:9/106k/105856/87215262/105856_3500_IMG_00_0000_max_476x317.jpeg",
          "url": "106k/105856/87215262/105856_3500_IMG_00_0000.jpeg",
          "caption": null
        },
        {
          "srcUrl": "https://media.rightmove.co.uk:443/dir/crop/10:9-16:9/106k/105856/87215262/105856_3500_IMG_01_0000_max_476x317.jpeg",
          "url": "106k/105856/87215262/105856_3500_IMG_01_0000.jpeg",
          "caption": null
        },
        {
          "srcUrl": "https://media.rightmove.co.uk:443/dir/crop/10:9-16:9/106k/105856/87215262/105856_3500_IMG_02_0000_max_476x317.jpeg",
          "url": "106k/105856/87215262/105856_3500_IMG_02_0000.jpeg",
          "caption": null
        },
        {
          "srcUrl": "https://media.rightmove.co.uk:443/dir/crop/10:9-16:9/106k/105856/87215262/105856_3500_IMG_03_0000_max_476x317.jpeg",
          "url": "106k/105856/87215262/105856_3500_IMG_03_0000.jpeg",
          "caption": null
        },
        {
          "srcUrl": "https://media.rightmove.co.uk:443/dir/crop/10:9-16:9/106k/105856/87215262/105856_3500_IMG_04_0000_max_476x317.jpeg",
          "url": "106k/105856/87215262/105856_3500_IMG_04_0000.jpeg",
          "caption": null
        }
      ],
      "mainImageSrc": "https://media.rightmove.co.uk:443/dir/crop/10:9-16:9/106k/105856/87215262/105856_3500_IMG_00_0000_max_476x317.jpeg",
      "mainMapImageSrc": "https://media.rightmove.co.uk:443/dir/crop/10:9-16:9/106k/105856/87215262/105856_3500_IMG_00_0000_max_296x197.jpeg"
    },
    "formattedBranchName": " by Residential Realtors, London",
    "addedOrReduced": "Added on 10/07/2025",
    "formattedDistance": "0.40 miles",
    "heading": "",
    "propertyTypeFullDescription": "3 bedroom flat",
    "displayStatus": "",
    "isRecent": false,
    "hasBrandPlus": true
  },
  {
    "id": 164146661,
    "bedrooms": 3,
    "bathrooms": 1,
    "numberOfImages": 10,
    "numberOfFloorplans": 1,
    "numberOfVirtualTours": 0,
    "summary": "***EAT IN KITCHEN***",
    "displayAddress": "Lenham House, Staple Street, SE1",
    "countryCode": "GB",
    "location": {
      "latitude": 51.4989,
      "longitude": -0.087132
    },
    "images": [
      {
        "srcUrl": "https://media.rightmove.co.uk:443/dir/crop/10:9-16:9/106k/105856/164146661/105856_3429_IMG_00_0000_max_476x317.jpeg",
        "url": "106k/105856/164146661/105856_3429_IMG_00_0000.jpeg",
        "caption": null
      },
      {
        "srcUrl": "https://media.rightmove.co.uk:443/dir/crop/10:9-16:9/106k/105856/164146661/105856_3429_IMG_01_0000_max_476x317.jpeg",
        "url": "106k/105856/164146661/105856_3429_IMG_01_0000.jpeg",
        "caption": null
      },
      {
        "srcUrl": "https://media.rightmove.co.uk:443/dir/crop/10:9-16:9/106k/105856/164146661/105856_3429_IMG_02_0000_max_476x317.jpeg",
        "url": "106k/105856/164146661/105856_3429_IMG_02_0000.jpeg",
        "caption": null
      },
      {
        "srcUrl": "https://media.rightmove.co.uk:443/dir/crop/10:9-16:9/106k/105856/164146661/105856_3429_IMG_03_0000_max_476x317.jpeg",
        "url": "106k/105856/164146661/105856_3429_IMG_03_0000.jpeg",
        "caption": null
      },
      {
        "srcUrl": "https://media.rightmove.co.uk:443/dir/crop/10:9-16:9/106k/105856/164146661/105856_3429_IMG_04_0000_max_476x317.jpeg",
        "url": "106k/105856/164146661/105856_3429_IMG_04_0000.jpeg",
        "caption": null
      },
      {
        "srcUrl": "https://media.rightmove.co.uk:443/dir/crop/10:9-16:9/106k/105856/164146661/105856_3429_IMG_05_0000_max_476x317.jpeg",
        "url": "106k/105856/164146661/105856_3429_IMG_05_0000.jpeg",
        "caption": null
      },
      {
        "srcUrl": "https://media.rightmove.co.uk:443/dir/crop/10:9-16:9/106k/105856/164146661/105856_3429_IMG_06_0000_max_476x317.jpeg",
        "url": "106k/105856/164146661/105856_3429_IMG_06_0000.jpeg",
        "caption": null
      },
      {
        "srcUrl": "https://media.rightmove.co.uk:443/dir/crop/10:9-16:9/106k/105856/164146661/105856_3429_IMG_07_0000_max_476x317.jpeg",
        "url": "106k/105856/164146661/105856_3429_IMG_07_0000.jpeg",
        "caption": null
      },
      {
        "srcUrl": "https://media.rightmove.co.uk:443/dir/crop/10:9-16:9/106k/105856/164146661/105856_3429_IMG_08_0000_max_476x317.jpeg",
        "url": "106k/105856/164146661/105856_3429_IMG_08_0000.jpeg",
        "caption": null
      },
      {
        "srcUrl": "https://media.rightmove.co.uk:443/dir/crop/10:9-16:9/106k/105856/164146661/105856_3429_IMG_09_0000_max_476x317.jpeg",
        "url": "106k/105856/164146661/105856_3429_IMG_09_0000.jpeg",
        "caption": null
      }
    ],
    "propertySubType": "Apartment",
    "tenure": {
      "tenureType": null
    },
    "letAvailableDate": "2025-09-14T00:00:00Z",
    "listingUpdate": {
      "listingUpdateReason": "price_reduced",
      "listingUpdateDate": "2025-07-10T14:52:17Z"
    },
    "price": {
      "amount": 720,
      "frequency": "weekly",
      "currencyCode": "GBP",
      "displayPrices": [
        {
          "displayPrice": "£3,120 pcm",
          "displayPriceQualifier": ""
        },
        {
          "displayPrice": "£720 pw",
          "displayPriceQualifier": ""
        }
      ]
    },
    "premiumListing": false,
    "featuredProperty": false,
    "customer": {
      "branchId": 105856,
      "brandPlusLogoURI": "/brand/brand_logo_45523_0001.png",
      "contactTelephone": "020 3834 8384",
      "branchDisplayName": "Residential Realtors, London",
      "branchName": "London",
      "brandTradingName": "Residential Realtors",
      "branchLandingPageUrl": "/estate-agents/agent/Residential-Realtors/London-105856.html",
      "development": false,
      "mediaServerUrl": "https://media.rightmove.co.uk:443",
      "showReducedProperties": true,
      "hasBrandPlus": true,
      "commercial": false,
      "showOnMap": true,
      "enhancedListing": false,
      "developmentContent": null,
      "buildToRent": false,
      "buildToRentBenefits": [],
      "updateDate": "2025-05-29T09:23:47Z",
      "brandPlusLogoUrl": "https://media.rightmove.co.uk:443/brand/brand_logo_45523_0001.png"
    },
    "distance": 0.4256,
    "transactionType": "rent",
    "productLabel": {
      "productLabelText": null,
      "spotlightLabel": false
    },
    "commercial": false,
    "development": false,
    "residential": true,
    "students": true,
    "auction": false,
    "feesApply": true,
    "feesApplyText": "No Agency Fees",
    "displaySize": "",
    "showOnMap": true,
    "propertyUrl": "/properties/164146661#/?channel=RES_LET",
    "contactUrl": "/property-to-rent/contactBranch.html?propertyId=164146661",
    "staticMapUrl": null,
    "channel": "RENT",
    "firstVisibleDate": "2025-07-04T02:32:49Z",
    "keywords": [],
    "keywordMatchType": "no_keyword",
    "saved": false,
    "hidden": false,
    "onlineViewingsAvailable": false,
    "lozengeModel": {
      "matchingLozenges": []
    },
    "streetView": {
      "showStreetView": true
    },
    "enquiredTimestamp": null,
    "updateDate": "2025-07-10T14:52:20Z",
    "enquiryAddedTimestamp": null,
    "enquiryCalledTimestamp": null,
    "enhancedListing": false,
    "propertyImages": {
      "images": [
        {
          "srcUrl": "https://media.rightmove.co.uk:443/dir/crop/10:9-16:9/106k/105856/164146661/105856_3429_IMG_00_0000_max_476x317.jpeg",
          "url": "106k/105856/164146661/105856_3429_IMG_00_0000.jpeg",
          "caption": null
        },
        {
          "srcUrl": "https://media.rightmove.co.uk:443/dir/crop/10:9-16:9/106k/105856/164146661/105856_3429_IMG_01_0000_max_476x317.jpeg",
          "url": "106k/105856/164146661/105856_3429_IMG_01_0000.jpeg",
          "caption": null
        },
        {
          "srcUrl": "https://media.rightmove.co.uk:443/dir/crop/10:9-16:9/106k/105856/164146661/105856_3429_IMG_02_0000_max_476x317.jpeg",
          "url": "106k/105856/164146661/105856_3429_IMG_02_0000.jpeg",
          "caption": null
        },
        {
          "srcUrl": "https://media.rightmove.co.uk:443/dir/crop/10:9-16:9/106k/105856/164146661/105856_3429_IMG_03_0000_max_476x317.jpeg",
          "url": "106k/105856/164146661/105856_3429_IMG_03_0000.jpeg",
          "caption": null
        },
        {
          "srcUrl": "https://media.rightmove.co.uk:443/dir/crop/10:9-16:9/106k/105856/164146661/105856_3429_IMG_04_0000_max_476x317.jpeg",
          "url": "106k/105856/164146661/105856_3429_IMG_04_0000.jpeg",
          "caption": null
        },
        {
          "srcUrl": "https://media.rightmove.co.uk:443/dir/crop/10:9-16:9/106k/105856/164146661/105856_3429_IMG_05_0000_max_476x317.jpeg",
          "url": "106k/105856/164146661/105856_3429_IMG_05_0000.jpeg",
          "caption": null
        },
        {
          "srcUrl": "https://media.rightmove.co.uk:443/dir/crop/10:9-16:9/106k/105856/164146661/105856_3429_IMG_06_0000_max_476x317.jpeg",
          "url": "106k/105856/164146661/105856_3429_IMG_06_0000.jpeg",
          "caption": null
        },
        {
          "srcUrl": "https://media.rightmove.co.uk:443/dir/crop/10:9-16:9/106k/105856/164146661/105856_3429_IMG_07_0000_max_476x317.jpeg",
          "url": "106k/105856/164146661/105856_3429_IMG_07_0000.jpeg",
          "caption": null
        },
        {
          "srcUrl": "https://media.rightmove.co.uk:443/dir/crop/10:9-16:9/106k/105856/164146661/105856_3429_IMG_08_0000_max_476x317.jpeg",
          "url": "106k/105856/164146661/105856_3429_IMG_08_0000.jpeg",
          "caption": null
        },
        {
          "srcUrl": "https://media.rightmove.co.uk:443/dir/crop/10:9-16:9/106k/105856/164146661/105856_3429_IMG_09_0000_max_476x317.jpeg",
          "url": "106k/105856/164146661/105856_3429_IMG_09_0000.jpeg",
          "caption": null
        }
      ],
      "mainImageSrc": "https://media.rightmove.co.uk:443/dir/crop/10:9-16:9/106k/105856/164146661/105856_3429_IMG_00_0000_max_476x317.jpeg",
      "mainMapImageSrc": "https://media.rightmove.co.uk:443/dir/crop/10:9-16:9/106k/105856/164146661/105856_3429_IMG_00_0000_max_296x197.jpeg"
    },
    "formattedBranchName": " by Residential Realtors, London",
    "addedOrReduced": "Reduced on 10/07/2025",
    "formattedDistance": "0.43 miles",
    "heading": "",
    "propertyTypeFullDescription": "3 bedroom apartment",
    "displayStatus": "",
    "isRecent": false,
    "hasBrandPlus": true
  },
  {
    "id": 163852013,
    "bedrooms": 3,
    "bathrooms": 1,
    "numberOfImages": 12,
    "numberOfFloorplans": 1,
    "numberOfVirtualTours": 1,
    "summary": "Spacious Three Bedroom HMO-Licensed Property To Rent Near Tower Bridge, SE1.",
    "displayAddress": "St. Olaves Estate, Druid Street, London, SE1",
    "countryCode": "GB",
    "location": {
      "latitude": 51.50275,
      "longitude": -0.07956
    },
    "images": [
      {
        "srcUrl": "https://media.rightmove.co.uk:443/dir/crop/10:9-16:9/283k/282164/163852013/282164_F59SOSE12EX_IMG_11_0000_max_476x317.jpeg",
        "url": "283k/282164/163852013/282164_F59SOSE12EX_IMG_11_0000.jpeg",
        "caption": null
      },
      {
        "srcUrl": "https://media.rightmove.co.uk:443/dir/crop/10:9-16:9/283k/282164/163852013/282164_F59SOSE12EX_IMG_10_0000_max_476x317.jpeg",
        "url": "283k/282164/163852013/282164_F59SOSE12EX_IMG_10_0000.jpeg",
        "caption": null
      },
      {
        "srcUrl": "https://media.rightmove.co.uk:443/dir/crop/10:9-16:9/283k/282164/163852013/282164_F59SOSE12EX_IMG_06_0000_max_476x317.jpeg",
        "url": "283k/282164/163852013/282164_F59SOSE12EX_IMG_06_0000.jpeg",
        "caption": null
      },
      {
        "srcUrl": "https://media.rightmove.co.uk:443/dir/crop/10:9-16:9/283k/282164/163852013/282164_F59SOSE12EX_IMG_09_0000_max_476x317.jpeg",
        "url": "283k/282164/163852013/282164_F59SOSE12EX_IMG_09_0000.jpeg",
        "caption": null
      },
      {
        "srcUrl": "https://media.rightmove.co.uk:443/dir/crop/10:9-16:9/283k/282164/163852013/282164_F59SOSE12EX_IMG_05_0000_max_476x317.jpeg",
        "url": "283k/282164/163852013/282164_F59SOSE12EX_IMG_05_0000.jpeg",
        "caption": null
      },
      {
        "srcUrl": "https://media.rightmove.co.uk:443/dir/crop/10:9-16:9/283k/282164/163852013/282164_F59SOSE12EX_IMG_04_0000_max_476x317.jpeg",
        "url": "283k/282164/163852013/282164_F59SOSE12EX_IMG_04_0000.jpeg",
        "caption": null
      },
      {
        "srcUrl": "https://media.rightmove.co.uk:443/dir/crop/10:9-16:9/283k/282164/163852013/282164_F59SOSE12EX_IMG_01_0000_max_476x317.jpeg",
        "url": "283k/282164/163852013/282164_F59SOSE12EX_IMG_01_0000.jpeg",
        "caption": null
      },
      {
        "srcUrl": "https://media.rightmove.co.uk:443/dir/crop/10:9-16:9/283k/282164/163852013/282164_F59SOSE12EX_IMG_00_0000_max_476x317.jpeg",
        "url": "283k/282164/163852013/282164_F59SOSE12EX_IMG_00_0000.jpeg",
        "caption": null
      },
      {
        "srcUrl": "https://media.rightmove.co.uk:443/dir/crop/10:9-16:9/283k/282164/163852013/282164_F59SOSE12EX_IMG_08_0000_max_476x317.jpeg",
        "url": "283k/282164/163852013/282164_F59SOSE12EX_IMG_08_0000.jpeg",
        "caption": null
      },
      {
        "srcUrl": "https://media.rightmove.co.uk:443/dir/crop/10:9-16:9/283k/282164/163852013/282164_F59SOSE12EX_IMG_03_0000_max_476x317.jpeg",
        "url": "283k/282164/163852013/282164_F59SOSE12EX_IMG_03_0000.jpeg",
        "caption": null
      },
      {
        "srcUrl": "https://media.rightmove.co.uk:443/dir/crop/10:9-16:9/283k/282164/163852013/282164_F59SOSE12EX_IMG_02_0000_max_476x317.jpeg",
        "url": "283k/282164/163852013/282164_F59SOSE12EX_IMG_02_0000.jpeg",
        "caption": null
      },
      {
        "srcUrl": "https://media.rightmove.co.uk:443/dir/crop/10:9-16:9/283k/282164/163852013/282164_F59SOSE12EX_IMG_07_0000_max_476x317.jpeg",
        "url": "283k/282164/163852013/282164_F59SOSE12EX_IMG_07_0000.jpeg",
        "caption": null
      }
    ],
    "propertySubType": "Maisonette",
    "tenure": {
      "tenureType": null
    },
    "letAvailableDate": "2025-08-26T00:00:00Z",
    "listingUpdate": {
      "listingUpdateReason": "price_reduced",
      "listingUpdateDate": "2025-07-08T17:42:07Z"
    },
    "price": {
      "amount": 3000,
      "frequency": "monthly",
      "currencyCode": "GBP",
      "displayPrices": [
        {
          "displayPrice": "£3,000 pcm",
          "displayPriceQualifier": ""
        },
        {
          "displayPrice": "£692 pw",
          "displayPriceQualifier": ""
        }
      ]
    },
    "premiumListing": false,
    "featuredProperty": false,
    "customer": {
      "branchId": 282164,
      "brandPlusLogoURI": "/283k/282164/branch_rmchoice_logo_282164_0000.jpeg",
      "contactTelephone": "020 4572 2399",
      "branchDisplayName": "Citiland Homes, London",
      "branchName": "London",
      "brandTradingName": "Citiland Homes",
      "branchLandingPageUrl": "/estate-agents/agent/Citiland-Homes/London-282164.html",
      "development": false,
      "mediaServerUrl": "https://media.rightmove.co.uk:443",
      "showReducedProperties": true,
      "hasBrandPlus": true,
      "commercial": false,
      "showOnMap": true,
      "enhancedListing": false,
      "developmentContent": null,
      "buildToRent": false,
      "buildToRentBenefits": [],
      "updateDate": "2025-06-21T09:23:30Z",
      "brandPlusLogoUrl": "https://media.rightmove.co.uk:443/283k/282164/branch_rmchoice_logo_282164_0000.jpeg"
    },
    "distance": 0.3226,
    "transactionType": "rent",
    "productLabel": {
      "productLabelText": null,
      "spotlightLabel": false
    },
    "commercial": false,
    "development": false,
    "residential": true,
    "students": true,
    "auction": false,
    "feesApply": true,
    "feesApplyText": "CMP from Property Mark Company Number: C0140977\nThe Property Ombudsman (TPO)",
    "displaySize": "",
    "showOnMap": true,
    "propertyUrl": "/properties/163852013#/?channel=RES_LET",
    "contactUrl": "/property-to-rent/contactBranch.html?propertyId=163852013",
    "staticMapUrl": null,
    "channel": "RENT",
    "firstVisibleDate": "2025-06-26T18:07:51Z",
    "keywords": [],
    "keywordMatchType": "no_keyword",
    "saved": false,
    "hidden": false,
    "onlineViewingsAvailable": false,
    "lozengeModel": {
      "matchingLozenges": []
    },
    "streetView": {
      "showStreetView": true
    },
    "enquiredTimestamp": null,
    "updateDate": "2025-07-11T15:33:16Z",
    "enquiryAddedTimestamp": null,
    "enquiryCalledTimestamp": null,
    "enhancedListing": false,
    "propertyImages": {
      "images": [
        {
          "srcUrl": "https://media.rightmove.co.uk:443/dir/crop/10:9-16:9/283k/282164/163852013/282164_F59SOSE12EX_IMG_11_0000_max_476x317.jpeg",
          "url": "283k/282164/163852013/282164_F59SOSE12EX_IMG_11_0000.jpeg",
          "caption": null
        },
        {
          "srcUrl": "https://media.rightmove.co.uk:443/dir/crop/10:9-16:9/283k/282164/163852013/282164_F59SOSE12EX_IMG_10_0000_max_476x317.jpeg",
          "url": "283k/282164/163852013/282164_F59SOSE12EX_IMG_10_0000.jpeg",
          "caption": null
        },
        {
          "srcUrl": "https://media.rightmove.co.uk:443/dir/crop/10:9-16:9/283k/282164/163852013/282164_F59SOSE12EX_IMG_06_0000_max_476x317.jpeg",
          "url": "283k/282164/163852013/282164_F59SOSE12EX_IMG_06_0000.jpeg",
          "caption": null
        },
        {
          "srcUrl": "https://media.rightmove.co.uk:443/dir/crop/10:9-16:9/283k/282164/163852013/282164_F59SOSE12EX_IMG_09_0000_max_476x317.jpeg",
          "url": "283k/282164/163852013/282164_F59SOSE12EX_IMG_09_0000.jpeg",
          "caption": null
        },
        {
          "srcUrl": "https://media.rightmove.co.uk:443/dir/crop/10:9-16:9/283k/282164/163852013/282164_F59SOSE12EX_IMG_05_0000_max_476x317.jpeg",
          "url": "283k/282164/163852013/282164_F59SOSE12EX_IMG_05_0000.jpeg",
          "caption": null
        },
        {
          "srcUrl": "https://media.rightmove.co.uk:443/dir/crop/10:9-16:9/283k/282164/163852013/282164_F59SOSE12EX_IMG_04_0000_max_476x317.jpeg",
          "url": "283k/282164/163852013/282164_F59SOSE12EX_IMG_04_0000.jpeg",
          "caption": null
        },
        {
          "srcUrl": "https://media.rightmove.co.uk:443/dir/crop/10:9-16:9/283k/282164/163852013/282164_F59SOSE12EX_IMG_01_0000_max_476x317.jpeg",
          "url": "283k/282164/163852013/282164_F59SOSE12EX_IMG_01_0000.jpeg",
          "caption": null
        },
        {
          "srcUrl": "https://media.rightmove.co.uk:443/dir/crop/10:9-16:9/283k/282164/163852013/282164_F59SOSE12EX_IMG_00_0000_max_476x317.jpeg",
          "url": "283k/282164/163852013/282164_F59SOSE12EX_IMG_00_0000.jpeg",
          "caption": null
        },
        {
          "srcUrl": "https://media.rightmove.co.uk:443/dir/crop/10:9-16:9/283k/282164/163852013/282164_F59SOSE12EX_IMG_08_0000_max_476x317.jpeg",
          "url": "283k/282164/163852013/282164_F59SOSE12EX_IMG_08_0000.jpeg",
          "caption": null
        },
        {
          "srcUrl": "https://media.rightmove.co.uk:443/dir/crop/10:9-16:9/283k/282164/163852013/282164_F59SOSE12EX_IMG_03_0000_max_476x317.jpeg",
          "url": "283k/282164/163852013/282164_F59SOSE12EX_IMG_03_0000.jpeg",
          "caption": null
        },
        {
          "srcUrl": "https://media.rightmove.co.uk:443/dir/crop/10:9-16:9/283k/282164/163852013/282164_F59SOSE12EX_IMG_02_0000_max_476x317.jpeg",
          "url": "283k/282164/163852013/282164_F59SOSE12EX_IMG_02_0000.jpeg",
          "caption": null
        },
        {
          "srcUrl": "https://media.rightmove.co.uk:443/dir/crop/10:9-16:9/283k/282164/163852013/282164_F59SOSE12EX_IMG_07_0000_max_476x317.jpeg",
          "url": "283k/282164/163852013/282164_F59SOSE12EX_IMG_07_0000.jpeg",
          "caption": null
        }
      ],
      "mainImageSrc": "https://media.rightmove.co.uk:443/dir/crop/10:9-16:9/283k/282164/163852013/282164_F59SOSE12EX_IMG_11_0000_max_476x317.jpeg",
      "mainMapImageSrc": "https://media.rightmove.co.uk:443/dir/crop/10:9-16:9/283k/282164/163852013/282164_F59SOSE12EX_IMG_11_0000_max_296x197.jpeg"
    },
    "formattedBranchName": " by Citiland Homes, London",
    "addedOrReduced": "Reduced on 08/07/2025",
    "formattedDistance": "0.32 miles",
    "heading": "",
    "propertyTypeFullDescription": "3 bedroom maisonette",
    "displayStatus": "",
    "isRecent": false,
    "hasBrandPlus": true
  },
  {
    "id": 87191781,
    "bedrooms": 3,
    "bathrooms": 1,
    "numberOfImages": 7,
    "numberOfFloorplans": 0,
    "numberOfVirtualTours": 0,
    "summary": "Residential Realtors are proud to present to the market this newly refurbished three bedroom apartment",
    "displayAddress": "Tabard Garden Estate, LONDON,, SE1",
    "countryCode": "GB",
    "location": {
      "latitude": 51.49919,
      "longitude": -0.08734
    },
    "images": [
      {
        "srcUrl": "https://media.rightmove.co.uk:443/dir/crop/10:9-16:9/106k/105856/87191781/105856_3499_IMG_05_0000_max_476x317.jpeg",
        "url": "106k/105856/87191781/105856_3499_IMG_05_0000.jpeg",
        "caption": null
      },
      {
        "srcUrl": "https://media.rightmove.co.uk:443/dir/crop/10:9-16:9/106k/105856/87191781/105856_3499_IMG_06_0000_max_476x317.jpeg",
        "url": "106k/105856/87191781/105856_3499_IMG_06_0000.jpeg",
        "caption": null
      },
      {
        "srcUrl": "https://media.rightmove.co.uk:443/dir/crop/10:9-16:9/106k/105856/87191781/105856_3499_IMG_00_0000_max_476x317.jpeg",
        "url": "106k/105856/87191781/105856_3499_IMG_00_0000.jpeg",
        "caption": null
      },
      {
        "srcUrl": "https://media.rightmove.co.uk:443/dir/crop/10:9-16:9/106k/105856/87191781/105856_3499_IMG_01_0000_max_476x317.jpeg",
        "url": "106k/105856/87191781/105856_3499_IMG_01_0000.jpeg",
        "caption": null
      },
      {
        "srcUrl": "https://media.rightmove.co.uk:443/dir/crop/10:9-16:9/106k/105856/87191781/105856_3499_IMG_02_0000_max_476x317.jpeg",
        "url": "106k/105856/87191781/105856_3499_IMG_02_0000.jpeg",
        "caption": null
      },
      {
        "srcUrl": "https://media.rightmove.co.uk:443/dir/crop/10:9-16:9/106k/105856/87191781/105856_3499_IMG_03_0000_max_476x317.jpeg",
        "url": "106k/105856/87191781/105856_3499_IMG_03_0000.jpeg",
        "caption": null
      },
      {
        "srcUrl": "https://media.rightmove.co.uk:443/dir/crop/10:9-16:9/106k/105856/87191781/105856_3499_IMG_04_0000_max_476x317.jpeg",
        "url": "106k/105856/87191781/105856_3499_IMG_04_0000.jpeg",
        "caption": null
      }
    ],
    "propertySubType": "Apartment",
    "tenure": {
      "tenureType": null
    },
    "letAvailableDate": "2025-08-16T00:00:00Z",
    "listingUpdate": {
      "listingUpdateReason": "new",
      "listingUpdateDate": "2025-07-07T16:54:04Z"
    },
    "price": {
      "amount": 750,
      "frequency": "weekly",
      "currencyCode": "GBP",
      "displayPrices": [
        {
          "displayPrice": "£3,250 pcm",
          "displayPriceQualifier": ""
        },
        {
          "displayPrice": "£750 pw",
          "displayPriceQualifier": ""
        }
      ]
    },
    "premiumListing": false,
    "featuredProperty": false,
    "customer": {
      "branchId": 105856,
      "brandPlusLogoURI": "/brand/brand_logo_45523_0001.png",
      "contactTelephone": "020 3834 8384",
      "branchDisplayName": "Residential Realtors, London",
      "branchName": "London",
      "brandTradingName": "Residential Realtors",
      "branchLandingPageUrl": "/estate-agents/agent/Residential-Realtors/London-105856.html",
      "development": false,
      "mediaServerUrl": "https://media.rightmove.co.uk:443",
      "showReducedProperties": true,
      "hasBrandPlus": true,
      "commercial": false,
      "showOnMap": true,
      "enhancedListing": false,
      "developmentContent": null,
      "buildToRent": false,
      "buildToRentBenefits": [],
      "updateDate": "2025-05-29T09:23:47Z",
      "brandPlusLogoUrl": "https://media.rightmove.co.uk:443/brand/brand_logo_45523_0001.png"
    },
    "distance": 0.4067,
    "transactionType": "rent",
    "productLabel": {
      "productLabelText": null,
      "spotlightLabel": false
    },
    "commercial": false,
    "development": false,
    "residential": true,
    "students": false,
    "auction": false,
    "feesApply": true,
    "feesApplyText": "No Agency Fees",
    "displaySize": "",
    "showOnMap": true,
    "propertyUrl": "/properties/87191781#/?channel=RES_LET",
    "contactUrl": "/property-to-rent/contactBranch.html?propertyId=87191781",
    "staticMapUrl": null,
    "channel": "RENT",
    "firstVisibleDate": "2025-07-10T11:57:11Z",
    "keywords": [],
    "keywordMatchType": "no_keyword",
    "saved": false,
    "hidden": false,
    "onlineViewingsAvailable": false,
    "lozengeModel": {
      "matchingLozenges": []
    },
    "streetView": {
      "showStreetView": true
    },
    "enquiredTimestamp": null,
    "updateDate": "2025-07-10T12:03:11Z",
    "enquiryAddedTimestamp": null,
    "enquiryCalledTimestamp": null,
    "enhancedListing": false,
    "propertyImages": {
      "images": [
        {
          "srcUrl": "https://media.rightmove.co.uk:443/dir/crop/10:9-16:9/106k/105856/87191781/105856_3499_IMG_05_0000_max_476x317.jpeg",
          "url": "106k/105856/87191781/105856_3499_IMG_05_0000.jpeg",
          "caption": null
        },
        {
          "srcUrl": "https://media.rightmove.co.uk:443/dir/crop/10:9-16:9/106k/105856/87191781/105856_3499_IMG_06_0000_max_476x317.jpeg",
          "url": "106k/105856/87191781/105856_3499_IMG_06_0000.jpeg",
          "caption": null
        },
        {
          "srcUrl": "https://media.rightmove.co.uk:443/dir/crop/10:9-16:9/106k/105856/87191781/105856_3499_IMG_00_0000_max_476x317.jpeg",
          "url": "106k/105856/87191781/105856_3499_IMG_00_0000.jpeg",
          "caption": null
        },
        {
          "srcUrl": "https://media.rightmove.co.uk:443/dir/crop/10:9-16:9/106k/105856/87191781/105856_3499_IMG_01_0000_max_476x317.jpeg",
          "url": "106k/105856/87191781/105856_3499_IMG_01_0000.jpeg",
          "caption": null
        },
        {
          "srcUrl": "https://media.rightmove.co.uk:443/dir/crop/10:9-16:9/106k/105856/87191781/105856_3499_IMG_02_0000_max_476x317.jpeg",
          "url": "106k/105856/87191781/105856_3499_IMG_02_0000.jpeg",
          "caption": null
        },
        {
          "srcUrl": "https://media.rightmove.co.uk:443/dir/crop/10:9-16:9/106k/105856/87191781/105856_3499_IMG_03_0000_max_476x317.jpeg",
          "url": "106k/105856/87191781/105856_3499_IMG_03_0000.jpeg",
          "caption": null
        },
        {
          "srcUrl": "https://media.rightmove.co.uk:443/dir/crop/10:9-16:9/106k/105856/87191781/105856_3499_IMG_04_0000_max_476x317.jpeg",
          "url": "106k/105856/87191781/105856_3499_IMG_04_0000.jpeg",
          "caption": null
        }
      ],
      "mainImageSrc": "https://media.rightmove.co.uk:443/dir/crop/10:9-16:9/106k/105856/87191781/105856_3499_IMG_05_0000_max_476x317.jpeg",
      "mainMapImageSrc": "https://media.rightmove.co.uk:443/dir/crop/10:9-16:9/106k/105856/87191781/105856_3499_IMG_05_0000_max_296x197.jpeg"
    },
    "formattedBranchName": " by Residential Realtors, London",
    "addedOrReduced": "Added on 07/07/2025",
    "formattedDistance": "0.41 miles",
    "heading": "",
    "propertyTypeFullDescription": "3 bedroom apartment",
    "displayStatus": "",
    "isRecent": false,
    "hasBrandPlus": true
  },
  {
    "id": 164252411,
    "bedrooms": 3,
    "bathrooms": 2,
    "numberOfImages": 9,
    "numberOfFloorplans": 1,
    "numberOfVirtualTours": 0,
    "summary": "We are pleased to market this stunning three bedroom flat in London Bridge. Conveniently located for the Shard, and within walking distance of the city, this flat is ideal for professional sharers (up to 4). The flat is fully furnished and has three good sized bedrooms, master with ensuite ...",
    "displayAddress": "Boughton House, Tennis Street, London",
    "countryCode": "GB",
    "location": {
      "latitude": 51.501982,
      "longitude": -0.09015
    },
    "images": [
      {
        "srcUrl": "https://media.rightmove.co.uk:443/dir/crop/10:9-16:9/275k/274583/164252411/274583_PWM-10686466_IMG_00_0000_max_476x317.jpeg",
        "url": "275k/274583/164252411/274583_PWM-10686466_IMG_00_0000.jpeg",
        "caption": "Photo 1"
      },
      {
        "srcUrl": "https://media.rightmove.co.uk:443/dir/crop/10:9-16:9/275k/274583/164252411/274583_PWM-10686466_IMG_01_0000_max_476x317.jpeg",
        "url": "275k/274583/164252411/274583_PWM-10686466_IMG_01_0000.jpeg",
        "caption": "Photo 2"
      },
      {
        "srcUrl": "https://media.rightmove.co.uk:443/dir/crop/10:9-16:9/275k/274583/164252411/274583_PWM-10686466_IMG_02_0000_max_476x317.jpeg",
        "url": "275k/274583/164252411/274583_PWM-10686466_IMG_02_0000.jpeg",
        "caption": "Photo 3"
      },
      {
        "srcUrl": "https://media.rightmove.co.uk:443/dir/crop/10:9-16:9/275k/274583/164252411/274583_PWM-10686466_IMG_03_0000_max_476x317.jpeg",
        "url": "275k/274583/164252411/274583_PWM-10686466_IMG_03_0000.jpeg",
        "caption": "Photo 7"
      },
      {
        "srcUrl": "https://media.rightmove.co.uk:443/dir/crop/10:9-16:9/275k/274583/164252411/274583_PWM-10686466_IMG_04_0000_max_476x317.jpeg",
        "url": "275k/274583/164252411/274583_PWM-10686466_IMG_04_0000.jpeg",
        "caption": "Photo 8"
      },
      {
        "srcUrl": "https://media.rightmove.co.uk:443/dir/crop/10:9-16:9/275k/274583/164252411/274583_PWM-10686466_IMG_05_0000_max_476x317.jpeg",
        "url": "275k/274583/164252411/274583_PWM-10686466_IMG_05_0000.jpeg",
        "caption": "Photo 5"
      },
      {
        "srcUrl": "https://media.rightmove.co.uk:443/dir/crop/10:9-16:9/275k/274583/164252411/274583_PWM-10686466_IMG_06_0000_max_476x317.jpeg",
        "url": "275k/274583/164252411/274583_PWM-10686466_IMG_06_0000.jpeg",
        "caption": "Photo 6"
      },
      {
        "srcUrl": "https://media.rightmove.co.uk:443/dir/crop/10:9-16:9/275k/274583/164252411/274583_PWM-10686466_IMG_07_0000_max_476x317.jpeg",
        "url": "275k/274583/164252411/274583_PWM-10686466_IMG_07_0000.jpeg",
        "caption": "Photo 4"
      },
      {
        "srcUrl": "https://media.rightmove.co.uk:443/dir/crop/10:9-16:9/275k/274583/164252411/274583_PWM-10686466_IMG_08_0000_max_476x317.jpeg",
        "url": "275k/274583/164252411/274583_PWM-10686466_IMG_08_0000.jpeg",
        "caption": "Photo 9"
      }
    ],
    "propertySubType": "Flat",
    "tenure": {
      "tenureType": null
    },
    "letAvailableDate": "2025-08-16T00:00:00Z",
    "listingUpdate": {
      "listingUpdateReason": "new",
      "listingUpdateDate": "2025-07-07T14:24:03Z"
    },
    "price": {
      "amount": 3500,
      "frequency": "monthly",
      "currencyCode": "GBP",
      "displayPrices": [
        {
          "displayPrice": "£3,500 pcm",
          "displayPriceQualifier": ""
        },
        {
          "displayPrice": "£808 pw",
          "displayPriceQualifier": ""
        }
      ]
    },
    "premiumListing": false,
    "featuredProperty": false,
    "customer": {
      "branchId": 274583,
      "brandPlusLogoURI": "/275k/274583/branch_rmchoice_logo_274583_0000.png",
      "contactTelephone": "020 3912 1985",
      "branchDisplayName": "PE Homes, West Molesey",
      "branchName": "West Molesey",
      "brandTradingName": "PE Homes",
      "branchLandingPageUrl": "/estate-agents/agent/PE-Homes/West-Molesey-274583.html",
      "development": false,
      "mediaServerUrl": "https://media.rightmove.co.uk:443",
      "showReducedProperties": true,
      "hasBrandPlus": true,
      "commercial": false,
      "showOnMap": true,
      "enhancedListing": false,
      "developmentContent": null,
      "buildToRent": false,
      "buildToRentBenefits": [],
      "updateDate": "2025-07-10T10:52:28Z",
      "brandPlusLogoUrl": "https://media.rightmove.co.uk:443/275k/274583/branch_rmchoice_logo_274583_0000.png"
    },
    "distance": 0.2735,
    "transactionType": "rent",
    "productLabel": {
      "productLabelText": null,
      "spotlightLabel": false
    },
    "commercial": false,
    "development": false,
    "residential": true,
    "students": false,
    "auction": false,
    "feesApply": true,
    "feesApplyText": null,
    "displaySize": "829 sq. ft.",
    "showOnMap": true,
    "propertyUrl": "/properties/164252411#/?channel=RES_LET",
    "contactUrl": "/property-to-rent/contactBranch.html?propertyId=164252411",
    "staticMapUrl": null,
    "channel": "RENT",
    "firstVisibleDate": "2025-07-07T14:18:04Z",
    "keywords": [],
    "keywordMatchType": "no_keyword",
    "saved": false,
    "hidden": false,
    "onlineViewingsAvailable": false,
    "lozengeModel": {
      "matchingLozenges": []
    },
    "streetView": {
      "showStreetView": true
    },
    "enquiredTimestamp": null,
    "updateDate": "2025-07-09T13:05:04Z",
    "enquiryAddedTimestamp": null,
    "enquiryCalledTimestamp": null,
    "enhancedListing": false,
    "propertyImages": {
      "images": [
        {
          "srcUrl": "https://media.rightmove.co.uk:443/dir/crop/10:9-16:9/275k/274583/164252411/274583_PWM-10686466_IMG_00_0000_max_476x317.jpeg",
          "url": "275k/274583/164252411/274583_PWM-10686466_IMG_00_0000.jpeg",
          "caption": "Photo 1"
        },
        {
          "srcUrl": "https://media.rightmove.co.uk:443/dir/crop/10:9-16:9/275k/274583/164252411/274583_PWM-10686466_IMG_01_0000_max_476x317.jpeg",
          "url": "275k/274583/164252411/274583_PWM-10686466_IMG_01_0000.jpeg",
          "caption": "Photo 2"
        },
        {
          "srcUrl": "https://media.rightmove.co.uk:443/dir/crop/10:9-16:9/275k/274583/164252411/274583_PWM-10686466_IMG_02_0000_max_476x317.jpeg",
          "url": "275k/274583/164252411/274583_PWM-10686466_IMG_02_0000.jpeg",
          "caption": "Photo 3"
        },
        {
          "srcUrl": "https://media.rightmove.co.uk:443/dir/crop/10:9-16:9/275k/274583/164252411/274583_PWM-10686466_IMG_03_0000_max_476x317.jpeg",
          "url": "275k/274583/164252411/274583_PWM-10686466_IMG_03_0000.jpeg",
          "caption": "Photo 7"
        },
        {
          "srcUrl": "https://media.rightmove.co.uk:443/dir/crop/10:9-16:9/275k/274583/164252411/274583_PWM-10686466_IMG_04_0000_max_476x317.jpeg",
          "url": "275k/274583/164252411/274583_PWM-10686466_IMG_04_0000.jpeg",
          "caption": "Photo 8"
        },
        {
          "srcUrl": "https://media.rightmove.co.uk:443/dir/crop/10:9-16:9/275k/274583/164252411/274583_PWM-10686466_IMG_05_0000_max_476x317.jpeg",
          "url": "275k/274583/164252411/274583_PWM-10686466_IMG_05_0000.jpeg",
          "caption": "Photo 5"
        },
        {
          "srcUrl": "https://media.rightmove.co.uk:443/dir/crop/10:9-16:9/275k/274583/164252411/274583_PWM-10686466_IMG_06_0000_max_476x317.jpeg",
          "url": "275k/274583/164252411/274583_PWM-10686466_IMG_06_0000.jpeg",
          "caption": "Photo 6"
        },
        {
          "srcUrl": "https://media.rightmove.co.uk:443/dir/crop/10:9-16:9/275k/274583/164252411/274583_PWM-10686466_IMG_07_0000_max_476x317.jpeg",
          "url": "275k/274583/164252411/274583_PWM-10686466_IMG_07_0000.jpeg",
          "caption": "Photo 4"
        },
        {
          "srcUrl": "https://media.rightmove.co.uk:443/dir/crop/10:9-16:9/275k/274583/164252411/274583_PWM-10686466_IMG_08_0000_max_476x317.jpeg",
          "url": "275k/274583/164252411/274583_PWM-10686466_IMG_08_0000.jpeg",
          "caption": "Photo 9"
        }
      ],
      "mainImageSrc": "https://media.rightmove.co.uk:443/dir/crop/10:9-16:9/275k/274583/164252411/274583_PWM-10686466_IMG_00_0000_max_476x317.jpeg",
      "mainMapImageSrc": "https://media.rightmove.co.uk:443/dir/crop/10:9-16:9/275k/274583/164252411/274583_PWM-10686466_IMG_00_0000_max_296x197.jpeg"
    },
    "formattedBranchName": " by PE Homes, West Molesey",
    "addedOrReduced": "Added on 07/07/2025",
    "formattedDistance": "0.27 miles",
    "heading": "",
    "propertyTypeFullDescription": "3 bedroom flat",
    "displayStatus": "",
    "isRecent": false,
    "hasBrandPlus": true
  },
  {
    "id": 164146667,
    "bedrooms": 3,
    "bathrooms": 1,
    "numberOfImages": 9,
    "numberOfFloorplans": 0,
    "numberOfVirtualTours": 0,
    "summary": "***7 Min Walk to Kings College London Guys Campus***",
    "displayAddress": "Great Dover Street, London, SE1",
    "countryCode": "GB",
    "location": {
      "latitude": 51.499186,
      "longitude": -0.091313
    },
    "images": [
      {
        "srcUrl": "https://media.rightmove.co.uk:443/dir/crop/10:9-16:9/106k/105856/164146667/105856_3235_IMG_00_0000_max_476x317.jpeg",
        "url": "106k/105856/164146667/105856_3235_IMG_00_0000.jpeg",
        "caption": null
      },
      {
        "srcUrl": "https://media.rightmove.co.uk:443/dir/crop/10:9-16:9/106k/105856/164146667/105856_3235_IMG_01_0000_max_476x317.jpeg",
        "url": "106k/105856/164146667/105856_3235_IMG_01_0000.jpeg",
        "caption": null
      },
      {
        "srcUrl": "https://media.rightmove.co.uk:443/dir/crop/10:9-16:9/106k/105856/164146667/105856_3235_IMG_02_0000_max_476x317.jpeg",
        "url": "106k/105856/164146667/105856_3235_IMG_02_0000.jpeg",
        "caption": null
      },
      {
        "srcUrl": "https://media.rightmove.co.uk:443/dir/crop/10:9-16:9/106k/105856/164146667/105856_3235_IMG_03_0000_max_476x317.jpeg",
        "url": "106k/105856/164146667/105856_3235_IMG_03_0000.jpeg",
        "caption": null
      },
      {
        "srcUrl": "https://media.rightmove.co.uk:443/dir/crop/10:9-16:9/106k/105856/164146667/105856_3235_IMG_04_0000_max_476x317.jpeg",
        "url": "106k/105856/164146667/105856_3235_IMG_04_0000.jpeg",
        "caption": null
      },
      {
        "srcUrl": "https://media.rightmove.co.uk:443/dir/crop/10:9-16:9/106k/105856/164146667/105856_3235_IMG_05_0000_max_476x317.jpeg",
        "url": "106k/105856/164146667/105856_3235_IMG_05_0000.jpeg",
        "caption": null
      },
      {
        "srcUrl": "https://media.rightmove.co.uk:443/dir/crop/10:9-16:9/106k/105856/164146667/105856_3235_IMG_06_0000_max_476x317.jpeg",
        "url": "106k/105856/164146667/105856_3235_IMG_06_0000.jpeg",
        "caption": null
      },
      {
        "srcUrl": "https://media.rightmove.co.uk:443/dir/crop/10:9-16:9/106k/105856/164146667/105856_3235_IMG_07_0000_max_476x317.jpeg",
        "url": "106k/105856/164146667/105856_3235_IMG_07_0000.jpeg",
        "caption": null
      },
      {
        "srcUrl": "https://media.rightmove.co.uk:443/dir/crop/10:9-16:9/106k/105856/164146667/105856_3235_IMG_08_0000_max_476x317.jpeg",
        "url": "106k/105856/164146667/105856_3235_IMG_08_0000.jpeg",
        "caption": null
      }
    ],
    "propertySubType": "Apartment",
    "tenure": {
      "tenureType": null
    },
    "letAvailableDate": "2024-09-14T00:00:00Z",
    "listingUpdate": {
      "listingUpdateReason": "price_reduced",
      "listingUpdateDate": "2025-07-04T02:40:01Z"
    },
    "price": {
      "amount": 646,
      "frequency": "weekly",
      "currencyCode": "GBP",
      "displayPrices": [
        {
          "displayPrice": "£2,799 pcm",
          "displayPriceQualifier": ""
        },
        {
          "displayPrice": "£646 pw",
          "displayPriceQualifier": ""
        }
      ]
    },
    "premiumListing": false,
    "featuredProperty": false,
    "customer": {
      "branchId": 105856,
      "brandPlusLogoURI": "/brand/brand_logo_45523_0001.png",
      "contactTelephone": "020 3834 8384",
      "branchDisplayName": "Residential Realtors, London",
      "branchName": "London",
      "brandTradingName": "Residential Realtors",
      "branchLandingPageUrl": "/estate-agents/agent/Residential-Realtors/London-105856.html",
      "development": false,
      "mediaServerUrl": "https://media.rightmove.co.uk:443",
      "showReducedProperties": true,
      "hasBrandPlus": true,
      "commercial": false,
      "showOnMap": true,
      "enhancedListing": false,
      "developmentContent": null,
      "buildToRent": false,
      "buildToRentBenefits": [],
      "updateDate": "2025-05-29T09:23:47Z",
      "brandPlusLogoUrl": "https://media.rightmove.co.uk:443/brand/brand_logo_45523_0001.png"
    },
    "distance": 0.4621,
    "transactionType": "rent",
    "productLabel": {
      "productLabelText": null,
      "spotlightLabel": false
    },
    "commercial": false,
    "development": false,
    "residential": true,
    "students": true,
    "auction": false,
    "feesApply": true,
    "feesApplyText": "No Agency Fees",
    "displaySize": "",
    "showOnMap": true,
    "propertyUrl": "/properties/164146667#/?channel=RES_LET",
    "contactUrl": "/property-to-rent/contactBranch.html?propertyId=164146667",
    "staticMapUrl": null,
    "channel": "RENT",
    "firstVisibleDate": "2025-07-04T02:34:10Z",
    "keywords": [],
    "keywordMatchType": "no_keyword",
    "saved": false,
    "hidden": false,
    "onlineViewingsAvailable": false,
    "lozengeModel": {
      "matchingLozenges": []
    },
    "streetView": {
      "showStreetView": true
    },
    "enquiredTimestamp": null,
    "updateDate": "2025-07-12T02:30:30Z",
    "enquiryAddedTimestamp": null,
    "enquiryCalledTimestamp": null,
    "enhancedListing": false,
    "propertyImages": {
      "images": [
        {
          "srcUrl": "https://media.rightmove.co.uk:443/dir/crop/10:9-16:9/106k/105856/164146667/105856_3235_IMG_00_0000_max_476x317.jpeg",
          "url": "106k/105856/164146667/105856_3235_IMG_00_0000.jpeg",
          "caption": null
        },
        {
          "srcUrl": "https://media.rightmove.co.uk:443/dir/crop/10:9-16:9/106k/105856/164146667/105856_3235_IMG_01_0000_max_476x317.jpeg",
          "url": "106k/105856/164146667/105856_3235_IMG_01_0000.jpeg",
          "caption": null
        },
        {
          "srcUrl": "https://media.rightmove.co.uk:443/dir/crop/10:9-16:9/106k/105856/164146667/105856_3235_IMG_02_0000_max_476x317.jpeg",
          "url": "106k/105856/164146667/105856_3235_IMG_02_0000.jpeg",
          "caption": null
        },
        {
          "srcUrl": "https://media.rightmove.co.uk:443/dir/crop/10:9-16:9/106k/105856/164146667/105856_3235_IMG_03_0000_max_476x317.jpeg",
          "url": "106k/105856/164146667/105856_3235_IMG_03_0000.jpeg",
          "caption": null
        },
        {
          "srcUrl": "https://media.rightmove.co.uk:443/dir/crop/10:9-16:9/106k/105856/164146667/105856_3235_IMG_04_0000_max_476x317.jpeg",
          "url": "106k/105856/164146667/105856_3235_IMG_04_0000.jpeg",
          "caption": null
        },
        {
          "srcUrl": "https://media.rightmove.co.uk:443/dir/crop/10:9-16:9/106k/105856/164146667/105856_3235_IMG_05_0000_max_476x317.jpeg",
          "url": "106k/105856/164146667/105856_3235_IMG_05_0000.jpeg",
          "caption": null
        },
        {
          "srcUrl": "https://media.rightmove.co.uk:443/dir/crop/10:9-16:9/106k/105856/164146667/105856_3235_IMG_06_0000_max_476x317.jpeg",
          "url": "106k/105856/164146667/105856_3235_IMG_06_0000.jpeg",
          "caption": null
        },
        {
          "srcUrl": "https://media.rightmove.co.uk:443/dir/crop/10:9-16:9/106k/105856/164146667/105856_3235_IMG_07_0000_max_476x317.jpeg",
          "url": "106k/105856/164146667/105856_3235_IMG_07_0000.jpeg",
          "caption": null
        },
        {
          "srcUrl": "https://media.rightmove.co.uk:443/dir/crop/10:9-16:9/106k/105856/164146667/105856_3235_IMG_08_0000_max_476x317.jpeg",
          "url": "106k/105856/164146667/105856_3235_IMG_08_0000.jpeg",
          "caption": null
        }
      ],
      "mainImageSrc": "https://media.rightmove.co.uk:443/dir/crop/10:9-16:9/106k/105856/164146667/105856_3235_IMG_00_0000_max_476x317.jpeg",
      "mainMapImageSrc": "https://media.rightmove.co.uk:443/dir/crop/10:9-16:9/106k/105856/164146667/105856_3235_IMG_00_0000_max_296x197.jpeg"
    },
    "formattedBranchName": " by Residential Realtors, London",
    "addedOrReduced": "Reduced on 04/07/2025",
    "formattedDistance": "0.46 miles",
    "heading": "",
    "propertyTypeFullDescription": "3 bedroom apartment",
    "displayStatus": "",
    "isRecent": false,
    "hasBrandPlus": true
  },
  {
    "id": 164066243,
    "bedrooms": 3,
    "bathrooms": 1,
    "numberOfImages": 12,
    "numberOfFloorplans": 0,
    "numberOfVirtualTours": 0,
    "summary": "Available from 15th August 2025 £2,800 PCM Just a 2-minute walk from King’s College Guy’s Campus, London Bridge, and Borough stations, this larger-than-average three ...",
    "displayAddress": "Medway House, 3 Bed Flat, London Bridge",
    "countryCode": "GB",
    "location": {
      "latitude": 51.49975,
      "longitude": -0.08847
    },
    "images": [
      {
        "srcUrl": "https://media.rightmove.co.uk:443/dir/crop/10:9-16:9/182k/181787/164066243/181787_181787_1139_IMG_00_0000_max_476x317.jpeg",
        "url": "182k/181787/164066243/181787_181787_1139_IMG_00_0000.jpeg",
        "caption": null
      },
      {
        "srcUrl": "https://media.rightmove.co.uk:443/dir/crop/10:9-16:9/182k/181787/164066243/181787_181787_1139_IMG_01_0000_max_476x317.jpeg",
        "url": "182k/181787/164066243/181787_181787_1139_IMG_01_0000.jpeg",
        "caption": null
      },
      {
        "srcUrl": "https://media.rightmove.co.uk:443/dir/crop/10:9-16:9/182k/181787/164066243/181787_181787_1139_IMG_02_0000_max_476x317.jpeg",
        "url": "182k/181787/164066243/181787_181787_1139_IMG_02_0000.jpeg",
        "caption": null
      },
      {
        "srcUrl": "https://media.rightmove.co.uk:443/dir/crop/10:9-16:9/182k/181787/164066243/181787_181787_1139_IMG_03_0000_max_476x317.jpeg",
        "url": "182k/181787/164066243/181787_181787_1139_IMG_03_0000.jpeg",
        "caption": null
      },
      {
        "srcUrl": "https://media.rightmove.co.uk:443/dir/crop/10:9-16:9/182k/181787/164066243/181787_181787_1139_IMG_04_0000_max_476x317.jpeg",
        "url": "182k/181787/164066243/181787_181787_1139_IMG_04_0000.jpeg",
        "caption": null
      },
      {
        "srcUrl": "https://media.rightmove.co.uk:443/dir/crop/10:9-16:9/182k/181787/164066243/181787_181787_1139_IMG_05_0000_max_476x317.jpeg",
        "url": "182k/181787/164066243/181787_181787_1139_IMG_05_0000.jpeg",
        "caption": null
      },
      {
        "srcUrl": "https://media.rightmove.co.uk:443/dir/crop/10:9-16:9/182k/181787/164066243/181787_181787_1139_IMG_06_0000_max_476x317.jpeg",
        "url": "182k/181787/164066243/181787_181787_1139_IMG_06_0000.jpeg",
        "caption": null
      },
      {
        "srcUrl": "https://media.rightmove.co.uk:443/dir/crop/10:9-16:9/182k/181787/164066243/181787_181787_1139_IMG_07_0000_max_476x317.jpeg",
        "url": "182k/181787/164066243/181787_181787_1139_IMG_07_0000.jpeg",
        "caption": null
      },
      {
        "srcUrl": "https://media.rightmove.co.uk:443/dir/crop/10:9-16:9/182k/181787/164066243/181787_181787_1139_IMG_08_0000_max_476x317.jpeg",
        "url": "182k/181787/164066243/181787_181787_1139_IMG_08_0000.jpeg",
        "caption": null
      },
      {
        "srcUrl": "https://media.rightmove.co.uk:443/dir/crop/10:9-16:9/182k/181787/164066243/181787_181787_1139_IMG_09_0000_max_476x317.jpeg",
        "url": "182k/181787/164066243/181787_181787_1139_IMG_09_0000.jpeg",
        "caption": null
      },
      {
        "srcUrl": "https://media.rightmove.co.uk:443/dir/crop/10:9-16:9/182k/181787/164066243/181787_181787_1139_IMG_10_0000_max_476x317.jpeg",
        "url": "182k/181787/164066243/181787_181787_1139_IMG_10_0000.jpeg",
        "caption": null
      },
      {
        "srcUrl": "https://media.rightmove.co.uk:443/dir/crop/10:9-16:9/182k/181787/164066243/181787_181787_1139_IMG_11_0000_max_476x317.jpeg",
        "url": "182k/181787/164066243/181787_181787_1139_IMG_11_0000.jpeg",
        "caption": null
      }
    ],
    "propertySubType": "Flat",
    "tenure": {
      "tenureType": null
    },
    "letAvailableDate": null,
    "listingUpdate": {
      "listingUpdateReason": "new",
      "listingUpdateDate": "2025-07-02T13:37:05Z"
    },
    "price": {
      "amount": 646,
      "frequency": "weekly",
      "currencyCode": "GBP",
      "displayPrices": [
        {
          "displayPrice": "£2,799 pcm",
          "displayPriceQualifier": ""
        },
        {
          "displayPrice": "£646 pw",
          "displayPriceQualifier": ""
        }
      ]
    },
    "premiumListing": false,
    "featuredProperty": false,
    "customer": {
      "branchId": 181787,
      "brandPlusLogoURI": "/company/clogo_rmchoice_55937_0000.png",
      "contactTelephone": "020 3910 6304",
      "branchDisplayName": "1 Ability Estate Agents, London",
      "branchName": "London",
      "brandTradingName": "1 Ability Estate Agents",
      "branchLandingPageUrl": "/estate-agents/agent/1-Ability-Estate-Agents/London-181787.html",
      "development": false,
      "mediaServerUrl": "https://media.rightmove.co.uk:443",
      "showReducedProperties": true,
      "hasBrandPlus": true,
      "commercial": false,
      "showOnMap": true,
      "enhancedListing": false,
      "developmentContent": null,
      "buildToRent": false,
      "buildToRentBenefits": [],
      "updateDate": "2025-05-29T11:17:48Z",
      "brandPlusLogoUrl": "https://media.rightmove.co.uk:443/company/clogo_rmchoice_55937_0000.png"
    },
    "distance": 0.3786,
    "transactionType": "rent",
    "productLabel": {
      "productLabelText": null,
      "spotlightLabel": false
    },
    "commercial": false,
    "development": false,
    "residential": true,
    "students": true,
    "auction": false,
    "feesApply": true,
    "feesApplyText": null,
    "displaySize": "",
    "showOnMap": true,
    "propertyUrl": "/properties/164066243#/?channel=RES_LET",
    "contactUrl": "/property-to-rent/contactBranch.html?propertyId=164066243",
    "staticMapUrl": null,
    "channel": "RENT",
    "firstVisibleDate": "2025-07-02T13:31:42Z",
    "keywords": [],
    "keywordMatchType": "no_keyword",
    "saved": false,
    "hidden": false,
    "onlineViewingsAvailable": false,
    "lozengeModel": {
      "matchingLozenges": []
    },
    "streetView": {
      "showStreetView": true
    },
    "enquiredTimestamp": null,
    "updateDate": "2025-07-02T13:37:05Z",
    "enquiryAddedTimestamp": null,
    "enquiryCalledTimestamp": null,
    "enhancedListing": false,
    "propertyImages": {
      "images": [
        {
          "srcUrl": "https://media.rightmove.co.uk:443/dir/crop/10:9-16:9/182k/181787/164066243/181787_181787_1139_IMG_00_0000_max_476x317.jpeg",
          "url": "182k/181787/164066243/181787_181787_1139_IMG_00_0000.jpeg",
          "caption": null
        },
        {
          "srcUrl": "https://media.rightmove.co.uk:443/dir/crop/10:9-16:9/182k/181787/164066243/181787_181787_1139_IMG_01_0000_max_476x317.jpeg",
          "url": "182k/181787/164066243/181787_181787_1139_IMG_01_0000.jpeg",
          "caption": null
        },
        {
          "srcUrl": "https://media.rightmove.co.uk:443/dir/crop/10:9-16:9/182k/181787/164066243/181787_181787_1139_IMG_02_0000_max_476x317.jpeg",
          "url": "182k/181787/164066243/181787_181787_1139_IMG_02_0000.jpeg",
          "caption": null
        },
        {
          "srcUrl": "https://media.rightmove.co.uk:443/dir/crop/10:9-16:9/182k/181787/164066243/181787_181787_1139_IMG_03_0000_max_476x317.jpeg",
          "url": "182k/181787/164066243/181787_181787_1139_IMG_03_0000.jpeg",
          "caption": null
        },
        {
          "srcUrl": "https://media.rightmove.co.uk:443/dir/crop/10:9-16:9/182k/181787/164066243/181787_181787_1139_IMG_04_0000_max_476x317.jpeg",
          "url": "182k/181787/164066243/181787_181787_1139_IMG_04_0000.jpeg",
          "caption": null
        },
        {
          "srcUrl": "https://media.rightmove.co.uk:443/dir/crop/10:9-16:9/182k/181787/164066243/181787_181787_1139_IMG_05_0000_max_476x317.jpeg",
          "url": "182k/181787/164066243/181787_181787_1139_IMG_05_0000.jpeg",
          "caption": null
        },
        {
          "srcUrl": "https://media.rightmove.co.uk:443/dir/crop/10:9-16:9/182k/181787/164066243/181787_181787_1139_IMG_06_0000_max_476x317.jpeg",
          "url": "182k/181787/164066243/181787_181787_1139_IMG_06_0000.jpeg",
          "caption": null
        },
        {
          "srcUrl": "https://media.rightmove.co.uk:443/dir/crop/10:9-16:9/182k/181787/164066243/181787_181787_1139_IMG_07_0000_max_476x317.jpeg",
          "url": "182k/181787/164066243/181787_181787_1139_IMG_07_0000.jpeg",
          "caption": null
        },
        {
          "srcUrl": "https://media.rightmove.co.uk:443/dir/crop/10:9-16:9/182k/181787/164066243/181787_181787_1139_IMG_08_0000_max_476x317.jpeg",
          "url": "182k/181787/164066243/181787_181787_1139_IMG_08_0000.jpeg",
          "caption": null
        },
        {
          "srcUrl": "https://media.rightmove.co.uk:443/dir/crop/10:9-16:9/182k/181787/164066243/181787_181787_1139_IMG_09_0000_max_476x317.jpeg",
          "url": "182k/181787/164066243/181787_181787_1139_IMG_09_0000.jpeg",
          "caption": null
        },
        {
          "srcUrl": "https://media.rightmove.co.uk:443/dir/crop/10:9-16:9/182k/181787/164066243/181787_181787_1139_IMG_10_0000_max_476x317.jpeg",
          "url": "182k/181787/164066243/181787_181787_1139_IMG_10_0000.jpeg",
          "caption": null
        },
        {
          "srcUrl": "https://media.rightmove.co.uk:443/dir/crop/10:9-16:9/182k/181787/164066243/181787_181787_1139_IMG_11_0000_max_476x317.jpeg",
          "url": "182k/181787/164066243/181787_181787_1139_IMG_11_0000.jpeg",
          "caption": null
        }
      ],
      "mainImageSrc": "https://media.rightmove.co.uk:443/dir/crop/10:9-16:9/182k/181787/164066243/181787_181787_1139_IMG_00_0000_max_476x317.jpeg",
      "mainMapImageSrc": "https://media.rightmove.co.uk:443/dir/crop/10:9-16:9/182k/181787/164066243/181787_181787_1139_IMG_00_0000_max_296x197.jpeg"
    },
    "formattedBranchName": " by 1 Ability Estate Agents, London",
    "addedOrReduced": "Added on 02/07/2025",
    "formattedDistance": "0.38 miles",
    "heading": "",
    "propertyTypeFullDescription": "3 bedroom flat",
    "displayStatus": "",
    "isRecent": false,
    "hasBrandPlus": true
  }
]